{
   "total": 6701,
   "total_pages": 336,
   "results": [
      {
         "id": "JdgMQOV7Lfc",
         "created_at": "2021-03-25T20:52:08-04:00",
         "updated_at": "2021-05-18T11:28:38-04:00",
         "promoted_at": null,
         "width": 3483,
         "height": 2763,
         "color": "#595959",
         "blur_hash": "L9EfTi~qxu-;~q_3%M%MIUIU-;%M",
         "description": "Morning commute",
         "alt_description": "grayscale photo of woman walking on pedestrian lane",
         "urls": {
            "raw": "https://images.unsplash.com/photo-1616719924608-5b278705e539?ixid=MnwxMjA3fDB8MXxzZWFyY2h8MTk2MXx8emVicmF8ZW58MHx8fHwxNjIxMzY4MDcy&ixlib=rb-1.2.1",
            "full": "https://images.unsplash.com/photo-1616719924608-5b278705e539?crop=entropy&cs=srgb&fm=jpg&ixid=MnwxMjA3fDB8MXxzZWFyY2h8MTk2MXx8emVicmF8ZW58MHx8fHwxNjIxMzY4MDcy&ixlib=rb-1.2.1&q=85",
            "regular": "https://images.unsplash.com/photo-1616719924608-5b278705e539?crop=entropy&cs=tinysrgb&fit=max&fm=jpg&ixid=MnwxMjA3fDB8MXxzZWFyY2h8MTk2MXx8emVicmF8ZW58MHx8fHwxNjIxMzY4MDcy&ixlib=rb-1.2.1&q=80&w=1080",
            "small": "https://images.unsplash.com/photo-1616719924608-5b278705e539?crop=entropy&cs=tinysrgb&fit=max&fm=jpg&ixid=MnwxMjA3fDB8MXxzZWFyY2h8MTk2MXx8emVicmF8ZW58MHx8fHwxNjIxMzY4MDcy&ixlib=rb-1.2.1&q=80&w=400",
            "thumb": "https://images.unsplash.com/photo-1616719924608-5b278705e539?crop=entropy&cs=tinysrgb&fit=max&fm=jpg&ixid=MnwxMjA3fDB8MXxzZWFyY2h8MTk2MXx8emVicmF8ZW58MHx8fHwxNjIxMzY4MDcy&ixlib=rb-1.2.1&q=80&w=200"
         },
         "links": {
            "self": "https://api.unsplash.com/photos/JdgMQOV7Lfc",
            "html": "https://unsplash.com/photos/JdgMQOV7Lfc",
            "download": "https://unsplash.com/photos/JdgMQOV7Lfc/download",
            "download_location": "https://api.unsplash.com/photos/JdgMQOV7Lfc/download?ixid=MnwxMjA3fDB8MXxzZWFyY2h8MTk2MXx8emVicmF8ZW58MHx8fHwxNjIxMzY4MDcy"
         },
         "categories": [],
         "likes": 0,
         "liked_by_user": false,
         "current_user_collections": [],
         "sponsorship": null,
         "user": {
            "id": "CMV2TlHk9qM",
            "updated_at": "2021-03-29T00:01:46-04:00",
            "username": "mgeslinphoto",
            "name": "Matthew Geslin",
            "first_name": "Matthew",
            "last_name": "Geslin",
            "twitter_username": null,
            "portfolio_url": null,
            "bio": null,
            "location": null,
            "links": {
               "self": "https://api.unsplash.com/users/mgeslinphoto",
               "html": "https://unsplash.com/@mgeslinphoto",
               "photos": "https://api.unsplash.com/users/mgeslinphoto/photos",
               "likes": "https://api.unsplash.com/users/mgeslinphoto/likes",
               "portfolio": "https://api.unsplash.com/users/mgeslinphoto/portfolio",
               "following": "https://api.unsplash.com/users/mgeslinphoto/following",
               "followers": "https://api.unsplash.com/users/mgeslinphoto/followers"
            },
            "profile_image": {
               "small": "https://images.unsplash.com/placeholder-avatars/extra-large.jpg?ixlib=rb-1.2.1&q=80&fm=jpg&crop=faces&cs=tinysrgb&fit=crop&h=32&w=32",
               "medium": "https://images.unsplash.com/placeholder-avatars/extra-large.jpg?ixlib=rb-1.2.1&q=80&fm=jpg&crop=faces&cs=tinysrgb&fit=crop&h=64&w=64",
               "large": "https://images.unsplash.com/placeholder-avatars/extra-large.jpg?ixlib=rb-1.2.1&q=80&fm=jpg&crop=faces&cs=tinysrgb&fit=crop&h=128&w=128"
            },
            "instagram_username": null,
            "total_collections": 0,
            "total_likes": 0,
            "total_photos": 2,
            "accepted_tos": true,
            "for_hire": false
         },
         "tags": [
            {
               "type": "search",
               "title": "asphalt"
            },
            {
               "type": "search",
               "title": "tarmac"
            },
            {
               "type": "search",
               "title": "road"
            }
         ]
      },
      {
         "id": "g3Vo3P8HrdQ",
         "created_at": "2020-10-08T16:45:58-04:00",
         "updated_at": "2021-05-18T04:19:47-04:00",
         "promoted_at": null,
         "width": 5509,
         "height": 3673,
         "color": "#0c4059",
         "blur_hash": "LRDTFi9ZR*Ri~UIUayRjtSf5f+ax",
         "description": "The exterior of the historic building hosting the Juvenile Court in Rome, Italy",
         "alt_description": "cars parked in front of brown building",
         "urls": {
            "raw": "https://images.unsplash.com/photo-1602189831128-7732a9398d83?ixid=MnwxMjA3fDB8MXxzZWFyY2h8MTk2Mnx8emVicmF8ZW58MHx8fHwxNjIxMzY4MDcy&ixlib=rb-1.2.1",
            "full": "https://images.unsplash.com/photo-1602189831128-7732a9398d83?crop=entropy&cs=srgb&fm=jpg&ixid=MnwxMjA3fDB8MXxzZWFyY2h8MTk2Mnx8emVicmF8ZW58MHx8fHwxNjIxMzY4MDcy&ixlib=rb-1.2.1&q=85",
            "regular": "https://images.unsplash.com/photo-1602189831128-7732a9398d83?crop=entropy&cs=tinysrgb&fit=max&fm=jpg&ixid=MnwxMjA3fDB8MXxzZWFyY2h8MTk2Mnx8emVicmF8ZW58MHx8fHwxNjIxMzY4MDcy&ixlib=rb-1.2.1&q=80&w=1080",
            "small": "https://images.unsplash.com/photo-1602189831128-7732a9398d83?crop=entropy&cs=tinysrgb&fit=max&fm=jpg&ixid=MnwxMjA3fDB8MXxzZWFyY2h8MTk2Mnx8emVicmF8ZW58MHx8fHwxNjIxMzY4MDcy&ixlib=rb-1.2.1&q=80&w=400",
            "thumb": "https://images.unsplash.com/photo-1602189831128-7732a9398d83?crop=entropy&cs=tinysrgb&fit=max&fm=jpg&ixid=MnwxMjA3fDB8MXxzZWFyY2h8MTk2Mnx8emVicmF8ZW58MHx8fHwxNjIxMzY4MDcy&ixlib=rb-1.2.1&q=80&w=200"
         },
         "links": {
            "self": "https://api.unsplash.com/photos/g3Vo3P8HrdQ",
            "html": "https://unsplash.com/photos/g3Vo3P8HrdQ",
            "download": "https://unsplash.com/photos/g3Vo3P8HrdQ/download",
            "download_location": "https://api.unsplash.com/photos/g3Vo3P8HrdQ/download?ixid=MnwxMjA3fDB8MXxzZWFyY2h8MTk2Mnx8emVicmF8ZW58MHx8fHwxNjIxMzY4MDcy"
         },
         "categories": [],
         "likes": 3,
         "liked_by_user": false,
         "current_user_collections": [],
         "sponsorship": null,
         "user": {
            "id": "nrldCMqj30A",
            "updated_at": "2021-05-18T15:30:28-04:00",
            "username": "gabiontheroad",
            "name": "Gabriella Clare Marino",
            "first_name": "Gabriella Clare",
            "last_name": "Marino",
            "twitter_username": "Nabu",
            "portfolio_url": "https://www.paypal.me/gabriellaclare",
            "bio": "Locked down in the most beautiful country in the world. You're welcome to use my art and I'd really appreciate if you could credit me! Instagram: @gabriella.clare & @gabriellaritratti\r\nIf you\u2019d like to support me, please consider a donation \u2661",
            "location": "Rome, Italy",
            "links": {
               "self": "https://api.unsplash.com/users/gabiontheroad",
               "html": "https://unsplash.com/@gabiontheroad",
               "photos": "https://api.unsplash.com/users/gabiontheroad/photos",
               "likes": "https://api.unsplash.com/users/gabiontheroad/likes",
               "portfolio": "https://api.unsplash.com/users/gabiontheroad/portfolio",
               "following": "https://api.unsplash.com/users/gabiontheroad/following",
               "followers": "https://api.unsplash.com/users/gabiontheroad/followers"
            },
            "profile_image": {
               "small": "https://images.unsplash.com/profile-1610121563931-2e3837cd81c0image?ixlib=rb-1.2.1&q=80&fm=jpg&crop=faces&cs=tinysrgb&fit=crop&h=32&w=32",
               "medium": "https://images.unsplash.com/profile-1610121563931-2e3837cd81c0image?ixlib=rb-1.2.1&q=80&fm=jpg&crop=faces&cs=tinysrgb&fit=crop&h=64&w=64",
               "large": "https://images.unsplash.com/profile-1610121563931-2e3837cd81c0image?ixlib=rb-1.2.1&q=80&fm=jpg&crop=faces&cs=tinysrgb&fit=crop&h=128&w=128"
            },
            "instagram_username": "gabriella.clare",
            "total_collections": 17,
            "total_likes": 907,
            "total_photos": 651,
            "accepted_tos": true,
            "for_hire": true
         },
         "tags": [
            {
               "type": "search",
               "title": "asphalt"
            },
            {
               "type": "search",
               "title": "tarmac"
            },
            {
               "type": "search",
               "title": "road"
            }
         ]
      },
      {
         "id": "SUj4iAt-5rI",
         "created_at": "2019-05-24T14:31:31-04:00",
         "updated_at": "2021-05-18T14:12:17-04:00",
         "promoted_at": "2019-05-25T05:16:35-04:00",
         "width": 3583,
         "height": 2376,
         "color": "#0c260c",
         "blur_hash": "LGBDNTD%tSIU~W9F%NR*x]D%s+Rj",
         "description": null,
         "alt_description": "person holding flowers near pedestrian",
         "urls": {
            "raw": "https://images.unsplash.com/photo-1558722630-717dde2b5cad?ixid=MnwxMjA3fDB8MXxzZWFyY2h8MTk2M3x8emVicmF8ZW58MHx8fHwxNjIxMzY4MDcy&ixlib=rb-1.2.1",
            "full": "https://images.unsplash.com/photo-1558722630-717dde2b5cad?crop=entropy&cs=srgb&fm=jpg&ixid=MnwxMjA3fDB8MXxzZWFyY2h8MTk2M3x8emVicmF8ZW58MHx8fHwxNjIxMzY4MDcy&ixlib=rb-1.2.1&q=85",
            "regular": "https://images.unsplash.com/photo-1558722630-717dde2b5cad?crop=entropy&cs=tinysrgb&fit=max&fm=jpg&ixid=MnwxMjA3fDB8MXxzZWFyY2h8MTk2M3x8emVicmF8ZW58MHx8fHwxNjIxMzY4MDcy&ixlib=rb-1.2.1&q=80&w=1080",
            "small": "https://images.unsplash.com/photo-1558722630-717dde2b5cad?crop=entropy&cs=tinysrgb&fit=max&fm=jpg&ixid=MnwxMjA3fDB8MXxzZWFyY2h8MTk2M3x8emVicmF8ZW58MHx8fHwxNjIxMzY4MDcy&ixlib=rb-1.2.1&q=80&w=400",
            "thumb": "https://images.unsplash.com/photo-1558722630-717dde2b5cad?crop=entropy&cs=tinysrgb&fit=max&fm=jpg&ixid=MnwxMjA3fDB8MXxzZWFyY2h8MTk2M3x8emVicmF8ZW58MHx8fHwxNjIxMzY4MDcy&ixlib=rb-1.2.1&q=80&w=200"
         },
         "links": {
            "self": "https://api.unsplash.com/photos/SUj4iAt-5rI",
            "html": "https://unsplash.com/photos/SUj4iAt-5rI",
            "download": "https://unsplash.com/photos/SUj4iAt-5rI/download",
            "download_location": "https://api.unsplash.com/photos/SUj4iAt-5rI/download?ixid=MnwxMjA3fDB8MXxzZWFyY2h8MTk2M3x8emVicmF8ZW58MHx8fHwxNjIxMzY4MDcy"
         },
         "categories": [],
         "likes": 82,
         "liked_by_user": false,
         "current_user_collections": [],
         "sponsorship": null,
         "user": {
            "id": "PxG_WFWcvmQ",
            "updated_at": "2021-05-12T12:18:29-04:00",
            "username": "marvinschwaibold",
            "name": "Marvin Schwaibold",
            "first_name": "Marvin",
            "last_name": "Schwaibold",
            "twitter_username": "MSchwaibold",
            "portfolio_url": "http://marvinschwaibold.com",
            "bio": "Web Concepts at Squarespace. Ex Art Director at Watson/DG. Jury member of FWA & AIGA.",
            "location": "New York",
            "links": {
               "self": "https://api.unsplash.com/users/marvinschwaibold",
               "html": "https://unsplash.com/@marvinschwaibold",
               "photos": "https://api.unsplash.com/users/marvinschwaibold/photos",
               "likes": "https://api.unsplash.com/users/marvinschwaibold/likes",
               "portfolio": "https://api.unsplash.com/users/marvinschwaibold/portfolio",
               "following": "https://api.unsplash.com/users/marvinschwaibold/following",
               "followers": "https://api.unsplash.com/users/marvinschwaibold/followers"
            },
            "profile_image": {
               "small": "https://images.unsplash.com/profile-1558722332526-0747ad3a45a3?ixlib=rb-1.2.1&q=80&fm=jpg&crop=faces&cs=tinysrgb&fit=crop&h=32&w=32",
               "medium": "https://images.unsplash.com/profile-1558722332526-0747ad3a45a3?ixlib=rb-1.2.1&q=80&fm=jpg&crop=faces&cs=tinysrgb&fit=crop&h=64&w=64",
               "large": "https://images.unsplash.com/profile-1558722332526-0747ad3a45a3?ixlib=rb-1.2.1&q=80&fm=jpg&crop=faces&cs=tinysrgb&fit=crop&h=128&w=128"
            },
            "instagram_username": "marvinschwaibold",
            "total_collections": 1,
            "total_likes": 0,
            "total_photos": 15,
            "accepted_tos": true,
            "for_hire": false
         },
         "tags": [
            {
               "type": "search",
               "title": "asphalt"
            },
            {
               "type": "search",
               "title": "tarmac"
            },
            {
               "type": "search",
               "title": "road"
            }
         ]
      },
      {
         "id": "g1_tP4FcCAk",
         "created_at": "2019-04-18T03:43:20-04:00",
         "updated_at": "2021-05-18T12:09:55-04:00",
         "promoted_at": null,
         "width": 4139,
         "height": 2764,
         "color": "#c0c0c0",
         "blur_hash": "LVF~%K4mV@x]_2IVWAt7o~Rjaeof",
         "description": null,
         "alt_description": "bus running on road",
         "urls": {
            "raw": "https://images.unsplash.com/photo-1555573367-ae3937497003?ixid=MnwxMjA3fDB8MXxzZWFyY2h8MTk2NHx8emVicmF8ZW58MHx8fHwxNjIxMzY4MDcy&ixlib=rb-1.2.1",
            "full": "https://images.unsplash.com/photo-1555573367-ae3937497003?crop=entropy&cs=srgb&fm=jpg&ixid=MnwxMjA3fDB8MXxzZWFyY2h8MTk2NHx8emVicmF8ZW58MHx8fHwxNjIxMzY4MDcy&ixlib=rb-1.2.1&q=85",
            "regular": "https://images.unsplash.com/photo-1555573367-ae3937497003?crop=entropy&cs=tinysrgb&fit=max&fm=jpg&ixid=MnwxMjA3fDB8MXxzZWFyY2h8MTk2NHx8emVicmF8ZW58MHx8fHwxNjIxMzY4MDcy&ixlib=rb-1.2.1&q=80&w=1080",
            "small": "https://images.unsplash.com/photo-1555573367-ae3937497003?crop=entropy&cs=tinysrgb&fit=max&fm=jpg&ixid=MnwxMjA3fDB8MXxzZWFyY2h8MTk2NHx8emVicmF8ZW58MHx8fHwxNjIxMzY4MDcy&ixlib=rb-1.2.1&q=80&w=400",
            "thumb": "https://images.unsplash.com/photo-1555573367-ae3937497003?crop=entropy&cs=tinysrgb&fit=max&fm=jpg&ixid=MnwxMjA3fDB8MXxzZWFyY2h8MTk2NHx8emVicmF8ZW58MHx8fHwxNjIxMzY4MDcy&ixlib=rb-1.2.1&q=80&w=200"
         },
         "links": {
            "self": "https://api.unsplash.com/photos/g1_tP4FcCAk",
            "html": "https://unsplash.com/photos/g1_tP4FcCAk",
            "download": "https://unsplash.com/photos/g1_tP4FcCAk/download",
            "download_location": "https://api.unsplash.com/photos/g1_tP4FcCAk/download?ixid=MnwxMjA3fDB8MXxzZWFyY2h8MTk2NHx8emVicmF8ZW58MHx8fHwxNjIxMzY4MDcy"
         },
         "categories": [],
         "likes": 16,
         "liked_by_user": false,
         "current_user_collections": [],
         "sponsorship": null,
         "user": {
            "id": "pamQnxK1Geo",
            "updated_at": "2021-05-17T05:38:22-04:00",
            "username": "struvictoryart",
            "name": "Victoria Strukovskaya",
            "first_name": "Victoria",
            "last_name": "Strukovskaya",
            "twitter_username": null,
            "portfolio_url": "https://www.instagram.com/struvictory.art/",
            "bio": "Hey there! My name is Victoria and I'm a photographer and an illustrator. Available for commission struvictory@gmail.com",
            "location": "Belarus",
            "links": {
               "self": "https://api.unsplash.com/users/struvictoryart",
               "html": "https://unsplash.com/@struvictoryart",
               "photos": "https://api.unsplash.com/users/struvictoryart/photos",
               "likes": "https://api.unsplash.com/users/struvictoryart/likes",
               "portfolio": "https://api.unsplash.com/users/struvictoryart/portfolio",
               "following": "https://api.unsplash.com/users/struvictoryart/following",
               "followers": "https://api.unsplash.com/users/struvictoryart/followers"
            },
            "profile_image": {
               "small": "https://images.unsplash.com/profile-1555599318036-070de73bf322?ixlib=rb-1.2.1&q=80&fm=jpg&crop=faces&cs=tinysrgb&fit=crop&h=32&w=32",
               "medium": "https://images.unsplash.com/profile-1555599318036-070de73bf322?ixlib=rb-1.2.1&q=80&fm=jpg&crop=faces&cs=tinysrgb&fit=crop&h=64&w=64",
               "large": "https://images.unsplash.com/profile-1555599318036-070de73bf322?ixlib=rb-1.2.1&q=80&fm=jpg&crop=faces&cs=tinysrgb&fit=crop&h=128&w=128"
            },
            "instagram_username": "struvictory.art",
            "total_collections": 0,
            "total_likes": 163,
            "total_photos": 35,
            "accepted_tos": true,
            "for_hire": false
         },
         "tags": [
            {
               "type": "search",
               "title": "asphalt"
            },
            {
               "type": "search",
               "title": "tarmac"
            },
            {
               "type": "search",
               "title": "road"
            }
         ]
      },
      {
         "id": "6zaEDQD5hMc",
         "created_at": "2021-04-12T02:49:23-04:00",
         "updated_at": "2021-05-16T14:56:30-04:00",
         "promoted_at": null,
         "width": 5568,
         "height": 3712,
         "color": "#262626",
         "blur_hash": "LOD0Juxu00IU~qxu9FIU?bt7D%Io",
         "description": null,
         "alt_description": "man in black jacket standing on the street",
         "urls": {
            "raw": "https://images.unsplash.com/photo-1618209983707-4db4c4be8df6?ixid=MnwxMjA3fDB8MXxzZWFyY2h8MTk2NXx8emVicmF8ZW58MHx8fHwxNjIxMzY4MDcy&ixlib=rb-1.2.1",
            "full": "https://images.unsplash.com/photo-1618209983707-4db4c4be8df6?crop=entropy&cs=srgb&fm=jpg&ixid=MnwxMjA3fDB8MXxzZWFyY2h8MTk2NXx8emVicmF8ZW58MHx8fHwxNjIxMzY4MDcy&ixlib=rb-1.2.1&q=85",
            "regular": "https://images.unsplash.com/photo-1618209983707-4db4c4be8df6?crop=entropy&cs=tinysrgb&fit=max&fm=jpg&ixid=MnwxMjA3fDB8MXxzZWFyY2h8MTk2NXx8emVicmF8ZW58MHx8fHwxNjIxMzY4MDcy&ixlib=rb-1.2.1&q=80&w=1080",
            "small": "https://images.unsplash.com/photo-1618209983707-4db4c4be8df6?crop=entropy&cs=tinysrgb&fit=max&fm=jpg&ixid=MnwxMjA3fDB8MXxzZWFyY2h8MTk2NXx8emVicmF8ZW58MHx8fHwxNjIxMzY4MDcy&ixlib=rb-1.2.1&q=80&w=400",
            "thumb": "https://images.unsplash.com/photo-1618209983707-4db4c4be8df6?crop=entropy&cs=tinysrgb&fit=max&fm=jpg&ixid=MnwxMjA3fDB8MXxzZWFyY2h8MTk2NXx8emVicmF8ZW58MHx8fHwxNjIxMzY4MDcy&ixlib=rb-1.2.1&q=80&w=200"
         },
         "links": {
            "self": "https://api.unsplash.com/photos/6zaEDQD5hMc",
            "html": "https://unsplash.com/photos/6zaEDQD5hMc",
            "download": "https://unsplash.com/photos/6zaEDQD5hMc/download",
            "download_location": "https://api.unsplash.com/photos/6zaEDQD5hMc/download?ixid=MnwxMjA3fDB8MXxzZWFyY2h8MTk2NXx8emVicmF8ZW58MHx8fHwxNjIxMzY4MDcy"
         },
         "categories": [],
         "likes": 0,
         "liked_by_user": false,
         "current_user_collections": [],
         "sponsorship": null,
         "user": {
            "id": "B1TepQxEajg",
            "updated_at": "2021-05-18T14:35:16-04:00",
            "username": "onthesearchforpineapples",
            "name": "Colin Lloyd",
            "first_name": "Colin",
            "last_name": "Lloyd",
            "twitter_username": "otsfpineapples",
            "portfolio_url": "https://cplloyd95.wixsite.com/otsfp",
            "bio": null,
            "location": "Denver, Colorado",
            "links": {
               "self": "https://api.unsplash.com/users/onthesearchforpineapples",
               "html": "https://unsplash.com/@onthesearchforpineapples",
               "photos": "https://api.unsplash.com/users/onthesearchforpineapples/photos",
               "likes": "https://api.unsplash.com/users/onthesearchforpineapples/likes",
               "portfolio": "https://api.unsplash.com/users/onthesearchforpineapples/portfolio",
               "following": "https://api.unsplash.com/users/onthesearchforpineapples/following",
               "followers": "https://api.unsplash.com/users/onthesearchforpineapples/followers"
            },
            "profile_image": {
               "small": "https://images.unsplash.com/profile-1616687073587-63950dc1079cimage?ixlib=rb-1.2.1&q=80&fm=jpg&crop=faces&cs=tinysrgb&fit=crop&h=32&w=32",
               "medium": "https://images.unsplash.com/profile-1616687073587-63950dc1079cimage?ixlib=rb-1.2.1&q=80&fm=jpg&crop=faces&cs=tinysrgb&fit=crop&h=64&w=64",
               "large": "https://images.unsplash.com/profile-1616687073587-63950dc1079cimage?ixlib=rb-1.2.1&q=80&fm=jpg&crop=faces&cs=tinysrgb&fit=crop&h=128&w=128"
            },
            "instagram_username": "onthesearchforpineapples",
            "total_collections": 0,
            "total_likes": 70,
            "total_photos": 628,
            "accepted_tos": true,
            "for_hire": true
         },
         "tags": [
            {
               "type": "search",
               "title": "asphalt"
            },
            {
               "type": "search",
               "title": "tarmac"
            },
            {
               "type": "search",
               "title": "road"
            }
         ]
      },
      {
         "id": "krry5aQViaY",
         "created_at": "2020-06-16T02:37:17-04:00",
         "updated_at": "2021-05-18T03:13:39-04:00",
         "promoted_at": null,
         "width": 4032,
         "height": 3024,
         "color": "#f3f3f3",
         "blur_hash": "LuLW;Ws9kCay?bV?ozWU~qbHWBay",
         "description": null,
         "alt_description": "2 men riding motorcycle in front of brown concrete building during daytime",
         "urls": {
            "raw": "https://images.unsplash.com/photo-1592289424123-82745c18ab7c?ixid=MnwxMjA3fDB8MXxzZWFyY2h8MTk2Nnx8emVicmF8ZW58MHx8fHwxNjIxMzY4MDcy&ixlib=rb-1.2.1",
            "full": "https://images.unsplash.com/photo-1592289424123-82745c18ab7c?crop=entropy&cs=srgb&fm=jpg&ixid=MnwxMjA3fDB8MXxzZWFyY2h8MTk2Nnx8emVicmF8ZW58MHx8fHwxNjIxMzY4MDcy&ixlib=rb-1.2.1&q=85",
            "regular": "https://images.unsplash.com/photo-1592289424123-82745c18ab7c?crop=entropy&cs=tinysrgb&fit=max&fm=jpg&ixid=MnwxMjA3fDB8MXxzZWFyY2h8MTk2Nnx8emVicmF8ZW58MHx8fHwxNjIxMzY4MDcy&ixlib=rb-1.2.1&q=80&w=1080",
            "small": "https://images.unsplash.com/photo-1592289424123-82745c18ab7c?crop=entropy&cs=tinysrgb&fit=max&fm=jpg&ixid=MnwxMjA3fDB8MXxzZWFyY2h8MTk2Nnx8emVicmF8ZW58MHx8fHwxNjIxMzY4MDcy&ixlib=rb-1.2.1&q=80&w=400",
            "thumb": "https://images.unsplash.com/photo-1592289424123-82745c18ab7c?crop=entropy&cs=tinysrgb&fit=max&fm=jpg&ixid=MnwxMjA3fDB8MXxzZWFyY2h8MTk2Nnx8emVicmF8ZW58MHx8fHwxNjIxMzY4MDcy&ixlib=rb-1.2.1&q=80&w=200"
         },
         "links": {
            "self": "https://api.unsplash.com/photos/krry5aQViaY",
            "html": "https://unsplash.com/photos/krry5aQViaY",
            "download": "https://unsplash.com/photos/krry5aQViaY/download",
            "download_location": "https://api.unsplash.com/photos/krry5aQViaY/download?ixid=MnwxMjA3fDB8MXxzZWFyY2h8MTk2Nnx8emVicmF8ZW58MHx8fHwxNjIxMzY4MDcy"
         },
         "categories": [],
         "likes": 12,
         "liked_by_user": false,
         "current_user_collections": [],
         "sponsorship": null,
         "user": {
            "id": "_8ghdcTkOWY",
            "updated_at": "2021-05-17T20:39:14-04:00",
            "username": "fin777",
            "name": "Deb Dowd",
            "first_name": "Deb",
            "last_name": "Dowd",
            "twitter_username": null,
            "portfolio_url": null,
            "bio": null,
            "location": "Queensland Australia",
            "links": {
               "self": "https://api.unsplash.com/users/fin777",
               "html": "https://unsplash.com/@fin777",
               "photos": "https://api.unsplash.com/users/fin777/photos",
               "likes": "https://api.unsplash.com/users/fin777/likes",
               "portfolio": "https://api.unsplash.com/users/fin777/portfolio",
               "following": "https://api.unsplash.com/users/fin777/following",
               "followers": "https://api.unsplash.com/users/fin777/followers"
            },
            "profile_image": {
               "small": "https://images.unsplash.com/profile-1586495434833-10bef52e4c03image?ixlib=rb-1.2.1&q=80&fm=jpg&crop=faces&cs=tinysrgb&fit=crop&h=32&w=32",
               "medium": "https://images.unsplash.com/profile-1586495434833-10bef52e4c03image?ixlib=rb-1.2.1&q=80&fm=jpg&crop=faces&cs=tinysrgb&fit=crop&h=64&w=64",
               "large": "https://images.unsplash.com/profile-1586495434833-10bef52e4c03image?ixlib=rb-1.2.1&q=80&fm=jpg&crop=faces&cs=tinysrgb&fit=crop&h=128&w=128"
            },
            "instagram_username": null,
            "total_collections": 5,
            "total_likes": 532,
            "total_photos": 271,
            "accepted_tos": true,
            "for_hire": false
         },
         "tags": [
            {
               "type": "search",
               "title": "asphalt"
            },
            {
               "type": "search",
               "title": "tarmac"
            },
            {
               "type": "search",
               "title": "road"
            }
         ]
      },
      {
         "id": "OPAUW5F7CQA",
         "created_at": "2020-05-04T07:50:32-04:00",
         "updated_at": "2021-05-18T02:13:15-04:00",
         "promoted_at": "2020-05-04T13:24:02-04:00",
         "width": 4000,
         "height": 5000,
         "color": "#f3f3f3",
         "blur_hash": "L=J8hXj[Rjay~qj[WBay%Mofofay",
         "description": "The Nike store in Namba area ",
         "alt_description": "people walking on pedestrian lane during daytime",
         "urls": {
            "raw": "https://images.unsplash.com/photo-1588592602795-653beb5b5267?ixid=MnwxMjA3fDB8MXxzZWFyY2h8MTk2N3x8emVicmF8ZW58MHx8fHwxNjIxMzY4MDcy&ixlib=rb-1.2.1",
            "full": "https://images.unsplash.com/photo-1588592602795-653beb5b5267?crop=entropy&cs=srgb&fm=jpg&ixid=MnwxMjA3fDB8MXxzZWFyY2h8MTk2N3x8emVicmF8ZW58MHx8fHwxNjIxMzY4MDcy&ixlib=rb-1.2.1&q=85",
            "regular": "https://images.unsplash.com/photo-1588592602795-653beb5b5267?crop=entropy&cs=tinysrgb&fit=max&fm=jpg&ixid=MnwxMjA3fDB8MXxzZWFyY2h8MTk2N3x8emVicmF8ZW58MHx8fHwxNjIxMzY4MDcy&ixlib=rb-1.2.1&q=80&w=1080",
            "small": "https://images.unsplash.com/photo-1588592602795-653beb5b5267?crop=entropy&cs=tinysrgb&fit=max&fm=jpg&ixid=MnwxMjA3fDB8MXxzZWFyY2h8MTk2N3x8emVicmF8ZW58MHx8fHwxNjIxMzY4MDcy&ixlib=rb-1.2.1&q=80&w=400",
            "thumb": "https://images.unsplash.com/photo-1588592602795-653beb5b5267?crop=entropy&cs=tinysrgb&fit=max&fm=jpg&ixid=MnwxMjA3fDB8MXxzZWFyY2h8MTk2N3x8emVicmF8ZW58MHx8fHwxNjIxMzY4MDcy&ixlib=rb-1.2.1&q=80&w=200"
         },
         "links": {
            "self": "https://api.unsplash.com/photos/OPAUW5F7CQA",
            "html": "https://unsplash.com/photos/OPAUW5F7CQA",
            "download": "https://unsplash.com/photos/OPAUW5F7CQA/download",
            "download_location": "https://api.unsplash.com/photos/OPAUW5F7CQA/download?ixid=MnwxMjA3fDB8MXxzZWFyY2h8MTk2N3x8emVicmF8ZW58MHx8fHwxNjIxMzY4MDcy"
         },
         "categories": [],
         "likes": 71,
         "liked_by_user": false,
         "current_user_collections": [],
         "sponsorship": null,
         "user": {
            "id": "Zw__Ud_ietA",
            "updated_at": "2021-05-15T18:41:27-04:00",
            "username": "jasonjrh",
            "name": "Jason Hazama",
            "first_name": "Jason",
            "last_name": "Hazama",
            "twitter_username": null,
            "portfolio_url": "https://vimeo.com/user96276875",
            "bio": "Hi, I'm Jason Hazama I'm a Content Creator based out of Osaka & Stockholm. @jasonjrh",
            "location": "Stockholm, Sweden",
            "links": {
               "self": "https://api.unsplash.com/users/jasonjrh",
               "html": "https://unsplash.com/@jasonjrh",
               "photos": "https://api.unsplash.com/users/jasonjrh/photos",
               "likes": "https://api.unsplash.com/users/jasonjrh/likes",
               "portfolio": "https://api.unsplash.com/users/jasonjrh/portfolio",
               "following": "https://api.unsplash.com/users/jasonjrh/following",
               "followers": "https://api.unsplash.com/users/jasonjrh/followers"
            },
            "profile_image": {
               "small": "https://images.unsplash.com/profile-1588588189745-f706b7b4839aimage?ixlib=rb-1.2.1&q=80&fm=jpg&crop=faces&cs=tinysrgb&fit=crop&h=32&w=32",
               "medium": "https://images.unsplash.com/profile-1588588189745-f706b7b4839aimage?ixlib=rb-1.2.1&q=80&fm=jpg&crop=faces&cs=tinysrgb&fit=crop&h=64&w=64",
               "large": "https://images.unsplash.com/profile-1588588189745-f706b7b4839aimage?ixlib=rb-1.2.1&q=80&fm=jpg&crop=faces&cs=tinysrgb&fit=crop&h=128&w=128"
            },
            "instagram_username": "jasonjrh",
            "total_collections": 1,
            "total_likes": 41,
            "total_photos": 8,
            "accepted_tos": true,
            "for_hire": false
         },
         "tags": [
            {
               "type": "search",
               "title": "asphalt"
            },
            {
               "type": "search",
               "title": "tarmac"
            },
            {
               "type": "search",
               "title": "road"
            }
         ]
      },
      {
         "id": "4UBNzj4Q-5E",
         "created_at": "2018-11-24T22:55:52-05:00",
         "updated_at": "2021-05-18T10:56:41-04:00",
         "promoted_at": null,
         "width": 4592,
         "height": 2584,
         "color": "#c0c0c0",
         "blur_hash": "LNM7ibxuIqof4m%MNJWBIUt7RkRj",
         "description": "Moving Tokyo",
         "alt_description": "person walking on pedestrian line",
         "urls": {
            "raw": "https://images.unsplash.com/photo-1543118136-6f42710b05d1?ixid=MnwxMjA3fDB8MXxzZWFyY2h8MTk2OHx8emVicmF8ZW58MHx8fHwxNjIxMzY4MDcy&ixlib=rb-1.2.1",
            "full": "https://images.unsplash.com/photo-1543118136-6f42710b05d1?crop=entropy&cs=srgb&fm=jpg&ixid=MnwxMjA3fDB8MXxzZWFyY2h8MTk2OHx8emVicmF8ZW58MHx8fHwxNjIxMzY4MDcy&ixlib=rb-1.2.1&q=85",
            "regular": "https://images.unsplash.com/photo-1543118136-6f42710b05d1?crop=entropy&cs=tinysrgb&fit=max&fm=jpg&ixid=MnwxMjA3fDB8MXxzZWFyY2h8MTk2OHx8emVicmF8ZW58MHx8fHwxNjIxMzY4MDcy&ixlib=rb-1.2.1&q=80&w=1080",
            "small": "https://images.unsplash.com/photo-1543118136-6f42710b05d1?crop=entropy&cs=tinysrgb&fit=max&fm=jpg&ixid=MnwxMjA3fDB8MXxzZWFyY2h8MTk2OHx8emVicmF8ZW58MHx8fHwxNjIxMzY4MDcy&ixlib=rb-1.2.1&q=80&w=400",
            "thumb": "https://images.unsplash.com/photo-1543118136-6f42710b05d1?crop=entropy&cs=tinysrgb&fit=max&fm=jpg&ixid=MnwxMjA3fDB8MXxzZWFyY2h8MTk2OHx8emVicmF8ZW58MHx8fHwxNjIxMzY4MDcy&ixlib=rb-1.2.1&q=80&w=200"
         },
         "links": {
            "self": "https://api.unsplash.com/photos/4UBNzj4Q-5E",
            "html": "https://unsplash.com/photos/4UBNzj4Q-5E",
            "download": "https://unsplash.com/photos/4UBNzj4Q-5E/download",
            "download_location": "https://api.unsplash.com/photos/4UBNzj4Q-5E/download?ixid=MnwxMjA3fDB8MXxzZWFyY2h8MTk2OHx8emVicmF8ZW58MHx8fHwxNjIxMzY4MDcy"
         },
         "categories": [],
         "likes": 72,
         "liked_by_user": false,
         "current_user_collections": [],
         "sponsorship": null,
         "user": {
            "id": "aq8oVMR1CYI",
            "updated_at": "2021-05-15T01:15:32-04:00",
            "username": "benihoudkhalil",
            "name": "Khalil Benihoud",
            "first_name": "Khalil",
            "last_name": "Benihoud",
            "twitter_username": "Benihoudkhalil",
            "portfolio_url": "http://www.youtube.com/c/KhalilBenihoud",
            "bio": "Product Designer @LedgerHQ \u2014 Creative guy & problem solver. ",
            "location": "Paris",
            "links": {
               "self": "https://api.unsplash.com/users/benihoudkhalil",
               "html": "https://unsplash.com/@benihoudkhalil",
               "photos": "https://api.unsplash.com/users/benihoudkhalil/photos",
               "likes": "https://api.unsplash.com/users/benihoudkhalil/likes",
               "portfolio": "https://api.unsplash.com/users/benihoudkhalil/portfolio",
               "following": "https://api.unsplash.com/users/benihoudkhalil/following",
               "followers": "https://api.unsplash.com/users/benihoudkhalil/followers"
            },
            "profile_image": {
               "small": "https://images.unsplash.com/profile-1514848283209-1abc6df4563d?ixlib=rb-1.2.1&q=80&fm=jpg&crop=faces&cs=tinysrgb&fit=crop&h=32&w=32",
               "medium": "https://images.unsplash.com/profile-1514848283209-1abc6df4563d?ixlib=rb-1.2.1&q=80&fm=jpg&crop=faces&cs=tinysrgb&fit=crop&h=64&w=64",
               "large": "https://images.unsplash.com/profile-1514848283209-1abc6df4563d?ixlib=rb-1.2.1&q=80&fm=jpg&crop=faces&cs=tinysrgb&fit=crop&h=128&w=128"
            },
            "instagram_username": "benihoudkhalil",
            "total_collections": 0,
            "total_likes": 75,
            "total_photos": 14,
            "accepted_tos": true,
            "for_hire": false
         },
         "tags": [
            {
               "type": "search",
               "title": "asphalt"
            },
            {
               "type": "search",
               "title": "tarmac"
            },
            {
               "type": "search",
               "title": "road"
            }
         ]
      },
      {
         "id": "s4gH7ZzJxp4",
         "created_at": "2019-10-06T11:42:01-04:00",
         "updated_at": "2021-05-17T22:09:52-04:00",
         "promoted_at": "2019-10-07T07:21:44-04:00",
         "width": 6000,
         "height": 4000,
         "color": "#262626",
         "blur_hash": "LE7LT2xuMwV[DNoztlaeS5M{RPkD",
         "description": null,
         "alt_description": "man standing on pedestrian lane",
         "urls": {
            "raw": "https://images.unsplash.com/photo-1570376240079-1b77104bcbad?ixid=MnwxMjA3fDB8MXxzZWFyY2h8MTk2OXx8emVicmF8ZW58MHx8fHwxNjIxMzY4MDcy&ixlib=rb-1.2.1",
            "full": "https://images.unsplash.com/photo-1570376240079-1b77104bcbad?crop=entropy&cs=srgb&fm=jpg&ixid=MnwxMjA3fDB8MXxzZWFyY2h8MTk2OXx8emVicmF8ZW58MHx8fHwxNjIxMzY4MDcy&ixlib=rb-1.2.1&q=85",
            "regular": "https://images.unsplash.com/photo-1570376240079-1b77104bcbad?crop=entropy&cs=tinysrgb&fit=max&fm=jpg&ixid=MnwxMjA3fDB8MXxzZWFyY2h8MTk2OXx8emVicmF8ZW58MHx8fHwxNjIxMzY4MDcy&ixlib=rb-1.2.1&q=80&w=1080",
            "small": "https://images.unsplash.com/photo-1570376240079-1b77104bcbad?crop=entropy&cs=tinysrgb&fit=max&fm=jpg&ixid=MnwxMjA3fDB8MXxzZWFyY2h8MTk2OXx8emVicmF8ZW58MHx8fHwxNjIxMzY4MDcy&ixlib=rb-1.2.1&q=80&w=400",
            "thumb": "https://images.unsplash.com/photo-1570376240079-1b77104bcbad?crop=entropy&cs=tinysrgb&fit=max&fm=jpg&ixid=MnwxMjA3fDB8MXxzZWFyY2h8MTk2OXx8emVicmF8ZW58MHx8fHwxNjIxMzY4MDcy&ixlib=rb-1.2.1&q=80&w=200"
         },
         "links": {
            "self": "https://api.unsplash.com/photos/s4gH7ZzJxp4",
            "html": "https://unsplash.com/photos/s4gH7ZzJxp4",
            "download": "https://unsplash.com/photos/s4gH7ZzJxp4/download",
            "download_location": "https://api.unsplash.com/photos/s4gH7ZzJxp4/download?ixid=MnwxMjA3fDB8MXxzZWFyY2h8MTk2OXx8emVicmF8ZW58MHx8fHwxNjIxMzY4MDcy"
         },
         "categories": [],
         "likes": 46,
         "liked_by_user": false,
         "current_user_collections": [],
         "sponsorship": null,
         "user": {
            "id": "GZD5POqhRyk",
            "updated_at": "2021-05-14T16:00:01-04:00",
            "username": "b_roamer",
            "name": "Rustem Baltiyev",
            "first_name": "Rustem",
            "last_name": "Baltiyev",
            "twitter_username": null,
            "portfolio_url": "https://www.instagram.com/b_roamer/",
            "bio": null,
            "location": "Almaty, Kazakhstan",
            "links": {
               "self": "https://api.unsplash.com/users/b_roamer",
               "html": "https://unsplash.com/@b_roamer",
               "photos": "https://api.unsplash.com/users/b_roamer/photos",
               "likes": "https://api.unsplash.com/users/b_roamer/likes",
               "portfolio": "https://api.unsplash.com/users/b_roamer/portfolio",
               "following": "https://api.unsplash.com/users/b_roamer/following",
               "followers": "https://api.unsplash.com/users/b_roamer/followers"
            },
            "profile_image": {
               "small": "https://images.unsplash.com/profile-1549908041507-3e77ad2b31de?ixlib=rb-1.2.1&q=80&fm=jpg&crop=faces&cs=tinysrgb&fit=crop&h=32&w=32",
               "medium": "https://images.unsplash.com/profile-1549908041507-3e77ad2b31de?ixlib=rb-1.2.1&q=80&fm=jpg&crop=faces&cs=tinysrgb&fit=crop&h=64&w=64",
               "large": "https://images.unsplash.com/profile-1549908041507-3e77ad2b31de?ixlib=rb-1.2.1&q=80&fm=jpg&crop=faces&cs=tinysrgb&fit=crop&h=128&w=128"
            },
            "instagram_username": "b_roamer",
            "total_collections": 0,
            "total_likes": 30,
            "total_photos": 57,
            "accepted_tos": true,
            "for_hire": false
         },
         "tags": [
            {
               "type": "search",
               "title": "asphalt"
            },
            {
               "type": "search",
               "title": "tarmac"
            },
            {
               "type": "search",
               "title": "road"
            }
         ]
      },
      {
         "id": "temPSdS_RZM",
         "created_at": "2019-07-24T15:34:37-04:00",
         "updated_at": "2021-05-18T05:08:06-04:00",
         "promoted_at": null,
         "width": 3967,
         "height": 3174,
         "color": "#262626",
         "blur_hash": "L58qQkWB?bj]5AkCbIWB00s.D*WC",
         "description": "Follow me on instagram @a.vzn",
         "alt_description": "two men standing beside black column",
         "urls": {
            "raw": "https://images.unsplash.com/photo-1563996869192-35186449bd13?ixid=MnwxMjA3fDB8MXxzZWFyY2h8MTk3MHx8emVicmF8ZW58MHx8fHwxNjIxMzY4MDcy&ixlib=rb-1.2.1",
            "full": "https://images.unsplash.com/photo-1563996869192-35186449bd13?crop=entropy&cs=srgb&fm=jpg&ixid=MnwxMjA3fDB8MXxzZWFyY2h8MTk3MHx8emVicmF8ZW58MHx8fHwxNjIxMzY4MDcy&ixlib=rb-1.2.1&q=85",
            "regular": "https://images.unsplash.com/photo-1563996869192-35186449bd13?crop=entropy&cs=tinysrgb&fit=max&fm=jpg&ixid=MnwxMjA3fDB8MXxzZWFyY2h8MTk3MHx8emVicmF8ZW58MHx8fHwxNjIxMzY4MDcy&ixlib=rb-1.2.1&q=80&w=1080",
            "small": "https://images.unsplash.com/photo-1563996869192-35186449bd13?crop=entropy&cs=tinysrgb&fit=max&fm=jpg&ixid=MnwxMjA3fDB8MXxzZWFyY2h8MTk3MHx8emVicmF8ZW58MHx8fHwxNjIxMzY4MDcy&ixlib=rb-1.2.1&q=80&w=400",
            "thumb": "https://images.unsplash.com/photo-1563996869192-35186449bd13?crop=entropy&cs=tinysrgb&fit=max&fm=jpg&ixid=MnwxMjA3fDB8MXxzZWFyY2h8MTk3MHx8emVicmF8ZW58MHx8fHwxNjIxMzY4MDcy&ixlib=rb-1.2.1&q=80&w=200"
         },
         "links": {
            "self": "https://api.unsplash.com/photos/temPSdS_RZM",
            "html": "https://unsplash.com/photos/temPSdS_RZM",
            "download": "https://unsplash.com/photos/temPSdS_RZM/download",
            "download_location": "https://api.unsplash.com/photos/temPSdS_RZM/download?ixid=MnwxMjA3fDB8MXxzZWFyY2h8MTk3MHx8emVicmF8ZW58MHx8fHwxNjIxMzY4MDcy"
         },
         "categories": [],
         "likes": 48,
         "liked_by_user": false,
         "current_user_collections": [],
         "sponsorship": null,
         "user": {
            "id": "YpHUhwpeLVw",
            "updated_at": "2021-05-16T23:32:54-04:00",
            "username": "aaronldsma",
            "name": "Aaron Ledesma",
            "first_name": "Aaron",
            "last_name": "Ledesma",
            "twitter_username": "aaronldsma",
            "portfolio_url": null,
            "bio": "Follow me on instagram @a.vzn for more",
            "location": "Toronto Ontario",
            "links": {
               "self": "https://api.unsplash.com/users/aaronldsma",
               "html": "https://unsplash.com/@aaronldsma",
               "photos": "https://api.unsplash.com/users/aaronldsma/photos",
               "likes": "https://api.unsplash.com/users/aaronldsma/likes",
               "portfolio": "https://api.unsplash.com/users/aaronldsma/portfolio",
               "following": "https://api.unsplash.com/users/aaronldsma/following",
               "followers": "https://api.unsplash.com/users/aaronldsma/followers"
            },
            "profile_image": {
               "small": "https://images.unsplash.com/placeholder-avatars/extra-large.jpg?ixlib=rb-1.2.1&q=80&fm=jpg&crop=faces&cs=tinysrgb&fit=crop&h=32&w=32",
               "medium": "https://images.unsplash.com/placeholder-avatars/extra-large.jpg?ixlib=rb-1.2.1&q=80&fm=jpg&crop=faces&cs=tinysrgb&fit=crop&h=64&w=64",
               "large": "https://images.unsplash.com/placeholder-avatars/extra-large.jpg?ixlib=rb-1.2.1&q=80&fm=jpg&crop=faces&cs=tinysrgb&fit=crop&h=128&w=128"
            },
            "instagram_username": "a.vzn",
            "total_collections": 1,
            "total_likes": 2,
            "total_photos": 39,
            "accepted_tos": true,
            "for_hire": false
         },
         "tags": [
            {
               "type": "search",
               "title": "asphalt"
            },
            {
               "type": "search",
               "title": "tarmac"
            },
            {
               "type": "search",
               "title": "human"
            }
         ]
      },
      {
         "id": "BCPO1qmZ6yU",
         "created_at": "2021-03-05T23:05:17-05:00",
         "updated_at": "2021-05-17T16:56:37-04:00",
         "promoted_at": null,
         "width": 5769,
         "height": 3846,
         "color": "#262626",
         "blur_hash": "LDBf@NDiD%-p00%MofRjX9WXRkWC",
         "description": null,
         "alt_description": "man in black jacket riding bicycle on road during daytime",
         "urls": {
            "raw": "https://images.unsplash.com/photo-1615003382009-b65717ef3aa0?ixid=MnwxMjA3fDB8MXxzZWFyY2h8MTk3MXx8emVicmF8ZW58MHx8fHwxNjIxMzY4MDcy&ixlib=rb-1.2.1",
            "full": "https://images.unsplash.com/photo-1615003382009-b65717ef3aa0?crop=entropy&cs=srgb&fm=jpg&ixid=MnwxMjA3fDB8MXxzZWFyY2h8MTk3MXx8emVicmF8ZW58MHx8fHwxNjIxMzY4MDcy&ixlib=rb-1.2.1&q=85",
            "regular": "https://images.unsplash.com/photo-1615003382009-b65717ef3aa0?crop=entropy&cs=tinysrgb&fit=max&fm=jpg&ixid=MnwxMjA3fDB8MXxzZWFyY2h8MTk3MXx8emVicmF8ZW58MHx8fHwxNjIxMzY4MDcy&ixlib=rb-1.2.1&q=80&w=1080",
            "small": "https://images.unsplash.com/photo-1615003382009-b65717ef3aa0?crop=entropy&cs=tinysrgb&fit=max&fm=jpg&ixid=MnwxMjA3fDB8MXxzZWFyY2h8MTk3MXx8emVicmF8ZW58MHx8fHwxNjIxMzY4MDcy&ixlib=rb-1.2.1&q=80&w=400",
            "thumb": "https://images.unsplash.com/photo-1615003382009-b65717ef3aa0?crop=entropy&cs=tinysrgb&fit=max&fm=jpg&ixid=MnwxMjA3fDB8MXxzZWFyY2h8MTk3MXx8emVicmF8ZW58MHx8fHwxNjIxMzY4MDcy&ixlib=rb-1.2.1&q=80&w=200"
         },
         "links": {
            "self": "https://api.unsplash.com/photos/BCPO1qmZ6yU",
            "html": "https://unsplash.com/photos/BCPO1qmZ6yU",
            "download": "https://unsplash.com/photos/BCPO1qmZ6yU/download",
            "download_location": "https://api.unsplash.com/photos/BCPO1qmZ6yU/download?ixid=MnwxMjA3fDB8MXxzZWFyY2h8MTk3MXx8emVicmF8ZW58MHx8fHwxNjIxMzY4MDcy"
         },
         "categories": [],
         "likes": 3,
         "liked_by_user": false,
         "current_user_collections": [],
         "sponsorship": null,
         "user": {
            "id": "tbd6vjyAmyo",
            "updated_at": "2021-05-17T15:07:51-04:00",
            "username": "miketmofficial",
            "name": "Michael Cox",
            "first_name": "Michael",
            "last_name": "Cox",
            "twitter_username": null,
            "portfolio_url": "http://iprefermike.com",
            "bio": null,
            "location": "Chicago",
            "links": {
               "self": "https://api.unsplash.com/users/miketmofficial",
               "html": "https://unsplash.com/@miketmofficial",
               "photos": "https://api.unsplash.com/users/miketmofficial/photos",
               "likes": "https://api.unsplash.com/users/miketmofficial/likes",
               "portfolio": "https://api.unsplash.com/users/miketmofficial/portfolio",
               "following": "https://api.unsplash.com/users/miketmofficial/following",
               "followers": "https://api.unsplash.com/users/miketmofficial/followers"
            },
            "profile_image": {
               "small": "https://images.unsplash.com/profile-1621278448903-a53af2858fb4image?ixlib=rb-1.2.1&q=80&fm=jpg&crop=faces&cs=tinysrgb&fit=crop&h=32&w=32",
               "medium": "https://images.unsplash.com/profile-1621278448903-a53af2858fb4image?ixlib=rb-1.2.1&q=80&fm=jpg&crop=faces&cs=tinysrgb&fit=crop&h=64&w=64",
               "large": "https://images.unsplash.com/profile-1621278448903-a53af2858fb4image?ixlib=rb-1.2.1&q=80&fm=jpg&crop=faces&cs=tinysrgb&fit=crop&h=128&w=128"
            },
            "instagram_username": "miketmofficial",
            "total_collections": 3,
            "total_likes": 1,
            "total_photos": 92,
            "accepted_tos": true,
            "for_hire": true
         },
         "tags": [
            {
               "type": "search",
               "title": "bike"
            },
            {
               "type": "search",
               "title": "vehicle"
            },
            {
               "type": "search",
               "title": "transportation"
            }
         ]
      },
      {
         "id": "cnCdzkwKtfk",
         "created_at": "2020-05-26T13:29:10-04:00",
         "updated_at": "2021-05-18T00:15:56-04:00",
         "promoted_at": null,
         "width": 3090,
         "height": 2048,
         "color": "#0c260c",
         "blur_hash": "LrF5v%t74:NG~Vt6E1Rj%1j[kCay",
         "description": "long drive",
         "alt_description": "cars on road near buildings during daytime",
         "urls": {
            "raw": "https://images.unsplash.com/photo-1590514142058-791c62f92b61?ixid=MnwxMjA3fDB8MXxzZWFyY2h8MTk3Mnx8emVicmF8ZW58MHx8fHwxNjIxMzY4MDcy&ixlib=rb-1.2.1",
            "full": "https://images.unsplash.com/photo-1590514142058-791c62f92b61?crop=entropy&cs=srgb&fm=jpg&ixid=MnwxMjA3fDB8MXxzZWFyY2h8MTk3Mnx8emVicmF8ZW58MHx8fHwxNjIxMzY4MDcy&ixlib=rb-1.2.1&q=85",
            "regular": "https://images.unsplash.com/photo-1590514142058-791c62f92b61?crop=entropy&cs=tinysrgb&fit=max&fm=jpg&ixid=MnwxMjA3fDB8MXxzZWFyY2h8MTk3Mnx8emVicmF8ZW58MHx8fHwxNjIxMzY4MDcy&ixlib=rb-1.2.1&q=80&w=1080",
            "small": "https://images.unsplash.com/photo-1590514142058-791c62f92b61?crop=entropy&cs=tinysrgb&fit=max&fm=jpg&ixid=MnwxMjA3fDB8MXxzZWFyY2h8MTk3Mnx8emVicmF8ZW58MHx8fHwxNjIxMzY4MDcy&ixlib=rb-1.2.1&q=80&w=400",
            "thumb": "https://images.unsplash.com/photo-1590514142058-791c62f92b61?crop=entropy&cs=tinysrgb&fit=max&fm=jpg&ixid=MnwxMjA3fDB8MXxzZWFyY2h8MTk3Mnx8emVicmF8ZW58MHx8fHwxNjIxMzY4MDcy&ixlib=rb-1.2.1&q=80&w=200"
         },
         "links": {
            "self": "https://api.unsplash.com/photos/cnCdzkwKtfk",
            "html": "https://unsplash.com/photos/cnCdzkwKtfk",
            "download": "https://unsplash.com/photos/cnCdzkwKtfk/download",
            "download_location": "https://api.unsplash.com/photos/cnCdzkwKtfk/download?ixid=MnwxMjA3fDB8MXxzZWFyY2h8MTk3Mnx8emVicmF8ZW58MHx8fHwxNjIxMzY4MDcy"
         },
         "categories": [],
         "likes": 20,
         "liked_by_user": false,
         "current_user_collections": [],
         "sponsorship": null,
         "user": {
            "id": "Xi78tDVHSO0",
            "updated_at": "2021-05-14T03:17:12-04:00",
            "username": "changhui",
            "name": "changhui lee",
            "first_name": "changhui",
            "last_name": "lee",
            "twitter_username": "blurfxo",
            "portfolio_url": "https://instagram.com/blureffect",
            "bio": "everything in life is so visual",
            "location": null,
            "links": {
               "self": "https://api.unsplash.com/users/changhui",
               "html": "https://unsplash.com/@changhui",
               "photos": "https://api.unsplash.com/users/changhui/photos",
               "likes": "https://api.unsplash.com/users/changhui/likes",
               "portfolio": "https://api.unsplash.com/users/changhui/portfolio",
               "following": "https://api.unsplash.com/users/changhui/following",
               "followers": "https://api.unsplash.com/users/changhui/followers"
            },
            "profile_image": {
               "small": "https://images.unsplash.com/profile-1604132876804-3ea7b9d149aeimage?ixlib=rb-1.2.1&q=80&fm=jpg&crop=faces&cs=tinysrgb&fit=crop&h=32&w=32",
               "medium": "https://images.unsplash.com/profile-1604132876804-3ea7b9d149aeimage?ixlib=rb-1.2.1&q=80&fm=jpg&crop=faces&cs=tinysrgb&fit=crop&h=64&w=64",
               "large": "https://images.unsplash.com/profile-1604132876804-3ea7b9d149aeimage?ixlib=rb-1.2.1&q=80&fm=jpg&crop=faces&cs=tinysrgb&fit=crop&h=128&w=128"
            },
            "instagram_username": "blureffect",
            "total_collections": 0,
            "total_likes": 4,
            "total_photos": 25,
            "accepted_tos": true,
            "for_hire": false
         },
         "tags": [
            {
               "type": "search",
               "title": "asphalt"
            },
            {
               "type": "search",
               "title": "tarmac"
            },
            {
               "type": "search",
               "title": "road"
            }
         ]
      },
      {
         "id": "5JM5gkgXuXA",
         "created_at": "2018-11-21T04:24:55-05:00",
         "updated_at": "2021-05-17T17:07:37-04:00",
         "promoted_at": null,
         "width": 5844,
         "height": 3834,
         "color": "#8c8c8c",
         "blur_hash": "LVHB*w%14mM{ozt7MwRP.8W?RjV@",
         "description": "This photo was taken on the middle of the road (as you can see), in a beautiful city at Sardinia. It was for a second not that busy, so I took my changes and stood in the middle of the road to take this shot.",
         "alt_description": "woman walking on sidewalk near pedestrian lane at daytime",
         "urls": {
            "raw": "https://images.unsplash.com/photo-1542792194-1a1dc5d63f5c?ixid=MnwxMjA3fDB8MXxzZWFyY2h8MTk3M3x8emVicmF8ZW58MHx8fHwxNjIxMzY4MDcy&ixlib=rb-1.2.1",
            "full": "https://images.unsplash.com/photo-1542792194-1a1dc5d63f5c?crop=entropy&cs=srgb&fm=jpg&ixid=MnwxMjA3fDB8MXxzZWFyY2h8MTk3M3x8emVicmF8ZW58MHx8fHwxNjIxMzY4MDcy&ixlib=rb-1.2.1&q=85",
            "regular": "https://images.unsplash.com/photo-1542792194-1a1dc5d63f5c?crop=entropy&cs=tinysrgb&fit=max&fm=jpg&ixid=MnwxMjA3fDB8MXxzZWFyY2h8MTk3M3x8emVicmF8ZW58MHx8fHwxNjIxMzY4MDcy&ixlib=rb-1.2.1&q=80&w=1080",
            "small": "https://images.unsplash.com/photo-1542792194-1a1dc5d63f5c?crop=entropy&cs=tinysrgb&fit=max&fm=jpg&ixid=MnwxMjA3fDB8MXxzZWFyY2h8MTk3M3x8emVicmF8ZW58MHx8fHwxNjIxMzY4MDcy&ixlib=rb-1.2.1&q=80&w=400",
            "thumb": "https://images.unsplash.com/photo-1542792194-1a1dc5d63f5c?crop=entropy&cs=tinysrgb&fit=max&fm=jpg&ixid=MnwxMjA3fDB8MXxzZWFyY2h8MTk3M3x8emVicmF8ZW58MHx8fHwxNjIxMzY4MDcy&ixlib=rb-1.2.1&q=80&w=200"
         },
         "links": {
            "self": "https://api.unsplash.com/photos/5JM5gkgXuXA",
            "html": "https://unsplash.com/photos/5JM5gkgXuXA",
            "download": "https://unsplash.com/photos/5JM5gkgXuXA/download",
            "download_location": "https://api.unsplash.com/photos/5JM5gkgXuXA/download?ixid=MnwxMjA3fDB8MXxzZWFyY2h8MTk3M3x8emVicmF8ZW58MHx8fHwxNjIxMzY4MDcy"
         },
         "categories": [],
         "likes": 88,
         "liked_by_user": false,
         "current_user_collections": [],
         "sponsorship": null,
         "user": {
            "id": "OzCXk-QzxUc",
            "updated_at": "2021-05-10T22:50:19-04:00",
            "username": "leoniechristine_visuals",
            "name": "Leonie Christine",
            "first_name": "Leonie",
            "last_name": "Christine",
            "twitter_username": null,
            "portfolio_url": null,
            "bio": null,
            "location": "Zwolle, The Netherlands",
            "links": {
               "self": "https://api.unsplash.com/users/leoniechristine_visuals",
               "html": "https://unsplash.com/@leoniechristine_visuals",
               "photos": "https://api.unsplash.com/users/leoniechristine_visuals/photos",
               "likes": "https://api.unsplash.com/users/leoniechristine_visuals/likes",
               "portfolio": "https://api.unsplash.com/users/leoniechristine_visuals/portfolio",
               "following": "https://api.unsplash.com/users/leoniechristine_visuals/following",
               "followers": "https://api.unsplash.com/users/leoniechristine_visuals/followers"
            },
            "profile_image": {
               "small": "https://images.unsplash.com/profile-1542793726511-38912f12cc8d?ixlib=rb-1.2.1&q=80&fm=jpg&crop=faces&cs=tinysrgb&fit=crop&h=32&w=32",
               "medium": "https://images.unsplash.com/profile-1542793726511-38912f12cc8d?ixlib=rb-1.2.1&q=80&fm=jpg&crop=faces&cs=tinysrgb&fit=crop&h=64&w=64",
               "large": "https://images.unsplash.com/profile-1542793726511-38912f12cc8d?ixlib=rb-1.2.1&q=80&fm=jpg&crop=faces&cs=tinysrgb&fit=crop&h=128&w=128"
            },
            "instagram_username": "leoniechristine.visuals",
            "total_collections": 2,
            "total_likes": 0,
            "total_photos": 9,
            "accepted_tos": true,
            "for_hire": false
         },
         "tags": [
            {
               "type": "search",
               "title": "asphalt"
            },
            {
               "type": "search",
               "title": "tarmac"
            },
            {
               "type": "search",
               "title": "road"
            }
         ]
      },
      {
         "id": "G6Fagp9bNKs",
         "created_at": "2020-02-09T14:19:51-05:00",
         "updated_at": "2021-05-18T02:11:38-04:00",
         "promoted_at": null,
         "width": 6000,
         "height": 4000,
         "color": "#260c0c",
         "blur_hash": "LIAl:[%1ENIW0#Rk$%xZIUnijuW=",
         "description": null,
         "alt_description": "black and white street light during night time",
         "urls": {
            "raw": "https://images.unsplash.com/photo-1581275933785-8e68f9918a6f?ixid=MnwxMjA3fDB8MXxzZWFyY2h8MTk3NHx8emVicmF8ZW58MHx8fHwxNjIxMzY4MDcy&ixlib=rb-1.2.1",
            "full": "https://images.unsplash.com/photo-1581275933785-8e68f9918a6f?crop=entropy&cs=srgb&fm=jpg&ixid=MnwxMjA3fDB8MXxzZWFyY2h8MTk3NHx8emVicmF8ZW58MHx8fHwxNjIxMzY4MDcy&ixlib=rb-1.2.1&q=85",
            "regular": "https://images.unsplash.com/photo-1581275933785-8e68f9918a6f?crop=entropy&cs=tinysrgb&fit=max&fm=jpg&ixid=MnwxMjA3fDB8MXxzZWFyY2h8MTk3NHx8emVicmF8ZW58MHx8fHwxNjIxMzY4MDcy&ixlib=rb-1.2.1&q=80&w=1080",
            "small": "https://images.unsplash.com/photo-1581275933785-8e68f9918a6f?crop=entropy&cs=tinysrgb&fit=max&fm=jpg&ixid=MnwxMjA3fDB8MXxzZWFyY2h8MTk3NHx8emVicmF8ZW58MHx8fHwxNjIxMzY4MDcy&ixlib=rb-1.2.1&q=80&w=400",
            "thumb": "https://images.unsplash.com/photo-1581275933785-8e68f9918a6f?crop=entropy&cs=tinysrgb&fit=max&fm=jpg&ixid=MnwxMjA3fDB8MXxzZWFyY2h8MTk3NHx8emVicmF8ZW58MHx8fHwxNjIxMzY4MDcy&ixlib=rb-1.2.1&q=80&w=200"
         },
         "links": {
            "self": "https://api.unsplash.com/photos/G6Fagp9bNKs",
            "html": "https://unsplash.com/photos/G6Fagp9bNKs",
            "download": "https://unsplash.com/photos/G6Fagp9bNKs/download",
            "download_location": "https://api.unsplash.com/photos/G6Fagp9bNKs/download?ixid=MnwxMjA3fDB8MXxzZWFyY2h8MTk3NHx8emVicmF8ZW58MHx8fHwxNjIxMzY4MDcy"
         },
         "categories": [],
         "likes": 4,
         "liked_by_user": false,
         "current_user_collections": [],
         "sponsorship": null,
         "user": {
            "id": "Lfzp070DKrw",
            "updated_at": "2021-05-18T11:53:08-04:00",
            "username": "leakingh",
            "name": "White",
            "first_name": "White",
            "last_name": null,
            "twitter_username": null,
            "portfolio_url": null,
            "bio": "instagram:leakingh",
            "location": "UAE",
            "links": {
               "self": "https://api.unsplash.com/users/leakingh",
               "html": "https://unsplash.com/@leakingh",
               "photos": "https://api.unsplash.com/users/leakingh/photos",
               "likes": "https://api.unsplash.com/users/leakingh/likes",
               "portfolio": "https://api.unsplash.com/users/leakingh/portfolio",
               "following": "https://api.unsplash.com/users/leakingh/following",
               "followers": "https://api.unsplash.com/users/leakingh/followers"
            },
            "profile_image": {
               "small": "https://images.unsplash.com/profile-1582046103811-a06077a63ed3image?ixlib=rb-1.2.1&q=80&fm=jpg&crop=faces&cs=tinysrgb&fit=crop&h=32&w=32",
               "medium": "https://images.unsplash.com/profile-1582046103811-a06077a63ed3image?ixlib=rb-1.2.1&q=80&fm=jpg&crop=faces&cs=tinysrgb&fit=crop&h=64&w=64",
               "large": "https://images.unsplash.com/profile-1582046103811-a06077a63ed3image?ixlib=rb-1.2.1&q=80&fm=jpg&crop=faces&cs=tinysrgb&fit=crop&h=128&w=128"
            },
            "instagram_username": "leakingh",
            "total_collections": 0,
            "total_likes": 0,
            "total_photos": 197,
            "accepted_tos": true,
            "for_hire": true
         },
         "tags": [
            {
               "type": "search",
               "title": "asphalt"
            },
            {
               "type": "search",
               "title": "tarmac"
            },
            {
               "type": "search",
               "title": "road"
            }
         ]
      },
      {
         "id": "iM_lH6zAWzA",
         "created_at": "2020-06-24T16:37:46-04:00",
         "updated_at": "2021-05-18T11:28:51-04:00",
         "promoted_at": null,
         "width": 4000,
         "height": 4000,
         "color": "#f3f3f3",
         "blur_hash": "LXKKsK~pt6tSNF%NbIxu%h%No#jE",
         "description": null,
         "alt_description": "man in white suit standing on sidewalk during daytime",
         "urls": {
            "raw": "https://images.unsplash.com/photo-1593030968015-851c86041b5a?ixid=MnwxMjA3fDB8MXxzZWFyY2h8MTk3NXx8emVicmF8ZW58MHx8fHwxNjIxMzY4MDcy&ixlib=rb-1.2.1",
            "full": "https://images.unsplash.com/photo-1593030968015-851c86041b5a?crop=entropy&cs=srgb&fm=jpg&ixid=MnwxMjA3fDB8MXxzZWFyY2h8MTk3NXx8emVicmF8ZW58MHx8fHwxNjIxMzY4MDcy&ixlib=rb-1.2.1&q=85",
            "regular": "https://images.unsplash.com/photo-1593030968015-851c86041b5a?crop=entropy&cs=tinysrgb&fit=max&fm=jpg&ixid=MnwxMjA3fDB8MXxzZWFyY2h8MTk3NXx8emVicmF8ZW58MHx8fHwxNjIxMzY4MDcy&ixlib=rb-1.2.1&q=80&w=1080",
            "small": "https://images.unsplash.com/photo-1593030968015-851c86041b5a?crop=entropy&cs=tinysrgb&fit=max&fm=jpg&ixid=MnwxMjA3fDB8MXxzZWFyY2h8MTk3NXx8emVicmF8ZW58MHx8fHwxNjIxMzY4MDcy&ixlib=rb-1.2.1&q=80&w=400",
            "thumb": "https://images.unsplash.com/photo-1593030968015-851c86041b5a?crop=entropy&cs=tinysrgb&fit=max&fm=jpg&ixid=MnwxMjA3fDB8MXxzZWFyY2h8MTk3NXx8emVicmF8ZW58MHx8fHwxNjIxMzY4MDcy&ixlib=rb-1.2.1&q=80&w=200"
         },
         "links": {
            "self": "https://api.unsplash.com/photos/iM_lH6zAWzA",
            "html": "https://unsplash.com/photos/iM_lH6zAWzA",
            "download": "https://unsplash.com/photos/iM_lH6zAWzA/download",
            "download_location": "https://api.unsplash.com/photos/iM_lH6zAWzA/download?ixid=MnwxMjA3fDB8MXxzZWFyY2h8MTk3NXx8emVicmF8ZW58MHx8fHwxNjIxMzY4MDcy"
         },
         "categories": [],
         "likes": 8,
         "liked_by_user": false,
         "current_user_collections": [],
         "sponsorship": null,
         "user": {
            "id": "_6IBhp-oOIY",
            "updated_at": "2021-05-18T08:55:11-04:00",
            "username": "dapperprofessional",
            "name": "Benjamin Rascoe",
            "first_name": "Benjamin",
            "last_name": "Rascoe",
            "twitter_username": "dapperpro",
            "portfolio_url": "http://dapperprofessional.com",
            "bio": "Thanks for checking out my pictures and profile! Photography has always been a passion of mine. My photos are a blend of landscape and fashion photography. When searching Unsplash for images I wanted to fill the gap between professional and amateur. ",
            "location": "Chicago",
            "links": {
               "self": "https://api.unsplash.com/users/dapperprofessional",
               "html": "https://unsplash.com/@dapperprofessional",
               "photos": "https://api.unsplash.com/users/dapperprofessional/photos",
               "likes": "https://api.unsplash.com/users/dapperprofessional/likes",
               "portfolio": "https://api.unsplash.com/users/dapperprofessional/portfolio",
               "following": "https://api.unsplash.com/users/dapperprofessional/following",
               "followers": "https://api.unsplash.com/users/dapperprofessional/followers"
            },
            "profile_image": {
               "small": "https://images.unsplash.com/profile-1593022018685-79e6dc219fb2image?ixlib=rb-1.2.1&q=80&fm=jpg&crop=faces&cs=tinysrgb&fit=crop&h=32&w=32",
               "medium": "https://images.unsplash.com/profile-1593022018685-79e6dc219fb2image?ixlib=rb-1.2.1&q=80&fm=jpg&crop=faces&cs=tinysrgb&fit=crop&h=64&w=64",
               "large": "https://images.unsplash.com/profile-1593022018685-79e6dc219fb2image?ixlib=rb-1.2.1&q=80&fm=jpg&crop=faces&cs=tinysrgb&fit=crop&h=128&w=128"
            },
            "instagram_username": "dapperprofessional",
            "total_collections": 12,
            "total_likes": 0,
            "total_photos": 501,
            "accepted_tos": true,
            "for_hire": false
         },
         "tags": [
            {
               "type": "search",
               "title": "asphalt"
            },
            {
               "type": "search",
               "title": "tarmac"
            },
            {
               "type": "search",
               "title": "apparel"
            }
         ]
      },
      {
         "id": "6opXPygpI2o",
         "created_at": "2020-10-24T07:56:06-04:00",
         "updated_at": "2021-05-18T04:24:24-04:00",
         "promoted_at": null,
         "width": 5444,
         "height": 3649,
         "color": "#262626",
         "blur_hash": "LC9a8I00?b9FRkIU-;IU-pM{t7WB",
         "description": null,
         "alt_description": null,
         "urls": {
            "raw": "https://images.unsplash.com/photo-1603540261450-1644a95a4e6b?ixid=MnwxMjA3fDB8MXxzZWFyY2h8MTk3Nnx8emVicmF8ZW58MHx8fHwxNjIxMzY4MDcy&ixlib=rb-1.2.1",
            "full": "https://images.unsplash.com/photo-1603540261450-1644a95a4e6b?crop=entropy&cs=srgb&fm=jpg&ixid=MnwxMjA3fDB8MXxzZWFyY2h8MTk3Nnx8emVicmF8ZW58MHx8fHwxNjIxMzY4MDcy&ixlib=rb-1.2.1&q=85",
            "regular": "https://images.unsplash.com/photo-1603540261450-1644a95a4e6b?crop=entropy&cs=tinysrgb&fit=max&fm=jpg&ixid=MnwxMjA3fDB8MXxzZWFyY2h8MTk3Nnx8emVicmF8ZW58MHx8fHwxNjIxMzY4MDcy&ixlib=rb-1.2.1&q=80&w=1080",
            "small": "https://images.unsplash.com/photo-1603540261450-1644a95a4e6b?crop=entropy&cs=tinysrgb&fit=max&fm=jpg&ixid=MnwxMjA3fDB8MXxzZWFyY2h8MTk3Nnx8emVicmF8ZW58MHx8fHwxNjIxMzY4MDcy&ixlib=rb-1.2.1&q=80&w=400",
            "thumb": "https://images.unsplash.com/photo-1603540261450-1644a95a4e6b?crop=entropy&cs=tinysrgb&fit=max&fm=jpg&ixid=MnwxMjA3fDB8MXxzZWFyY2h8MTk3Nnx8emVicmF8ZW58MHx8fHwxNjIxMzY4MDcy&ixlib=rb-1.2.1&q=80&w=200"
         },
         "links": {
            "self": "https://api.unsplash.com/photos/6opXPygpI2o",
            "html": "https://unsplash.com/photos/6opXPygpI2o",
            "download": "https://unsplash.com/photos/6opXPygpI2o/download",
            "download_location": "https://api.unsplash.com/photos/6opXPygpI2o/download?ixid=MnwxMjA3fDB8MXxzZWFyY2h8MTk3Nnx8emVicmF8ZW58MHx8fHwxNjIxMzY4MDcy"
         },
         "categories": [],
         "likes": 3,
         "liked_by_user": false,
         "current_user_collections": [],
         "sponsorship": null,
         "user": {
            "id": "I71Ylx7n8lY",
            "updated_at": "2021-05-18T12:35:23-04:00",
            "username": "krissmas",
            "name": "Krismas",
            "first_name": "Krismas",
            "last_name": null,
            "twitter_username": null,
            "portfolio_url": "https://instagram.com/____krismas_16?igshid=yfi0voiszgsq",
            "bio": null,
            "location": null,
            "links": {
               "self": "https://api.unsplash.com/users/krissmas",
               "html": "https://unsplash.com/@krissmas",
               "photos": "https://api.unsplash.com/users/krissmas/photos",
               "likes": "https://api.unsplash.com/users/krissmas/likes",
               "portfolio": "https://api.unsplash.com/users/krissmas/portfolio",
               "following": "https://api.unsplash.com/users/krissmas/following",
               "followers": "https://api.unsplash.com/users/krissmas/followers"
            },
            "profile_image": {
               "small": "https://images.unsplash.com/profile-1598527219433-a328994bebf7image?ixlib=rb-1.2.1&q=80&fm=jpg&crop=faces&cs=tinysrgb&fit=crop&h=32&w=32",
               "medium": "https://images.unsplash.com/profile-1598527219433-a328994bebf7image?ixlib=rb-1.2.1&q=80&fm=jpg&crop=faces&cs=tinysrgb&fit=crop&h=64&w=64",
               "large": "https://images.unsplash.com/profile-1598527219433-a328994bebf7image?ixlib=rb-1.2.1&q=80&fm=jpg&crop=faces&cs=tinysrgb&fit=crop&h=128&w=128"
            },
            "instagram_username": "____kristina_16",
            "total_collections": 0,
            "total_likes": 150,
            "total_photos": 33,
            "accepted_tos": true,
            "for_hire": false
         },
         "tags": [
            {
               "type": "search",
               "title": "human"
            },
            {
               "type": "search",
               "title": "pedestrian"
            },
            {
               "type": "landing_page",
               "title": "person",
               "source": {
                  "ancestry": {
                     "type": {
                        "slug": "images",
                        "pretty_slug": "Images"
                     },
                     "category": {
                        "slug": "people",
                        "pretty_slug": "People"
                     }
                  },
                  "title": "People Images & Pictures",
                  "subtitle": "Download free people images",
                  "description": "Human faces speak to us in a way that language cannot. Everyone recognize a smile, a frown, tears. Unsplash has the finest selection of people images on the web: high-def and curated for quality. Family, friends, men, women, Unsplash has photos for all.",
                  "meta_title": "People Pictures [HQ] | Download Free Images on Unsplash",
                  "meta_description": "Choose from hundreds of free people pictures. Download HD people photos for free on Unsplash.",
                  "cover_photo": {
                     "id": "PmNjS6b3XP4",
                     "created_at": "2017-04-20T18:04:07-04:00",
                     "updated_at": "2021-05-17T03:01:30-04:00",
                     "promoted_at": "2017-04-21T12:00:49-04:00",
                     "width": 4630,
                     "height": 3087,
                     "color": "#a6d9d9",
                     "blur_hash": "LjI=x%:QUbv#NHWVa}kCt7jFjZfQ",
                     "description": "Summer in France with baby",
                     "alt_description": "woman carrying baby while walking",
                     "urls": {
                        "raw": "https://images.unsplash.com/photo-1492725764893-90b379c2b6e7?ixlib=rb-1.2.1",
                        "full": "https://images.unsplash.com/photo-1492725764893-90b379c2b6e7?ixlib=rb-1.2.1&q=85&fm=jpg&crop=entropy&cs=srgb",
                        "regular": "https://images.unsplash.com/photo-1492725764893-90b379c2b6e7?ixlib=rb-1.2.1&q=80&fm=jpg&crop=entropy&cs=tinysrgb&w=1080&fit=max",
                        "small": "https://images.unsplash.com/photo-1492725764893-90b379c2b6e7?ixlib=rb-1.2.1&q=80&fm=jpg&crop=entropy&cs=tinysrgb&w=400&fit=max",
                        "thumb": "https://images.unsplash.com/photo-1492725764893-90b379c2b6e7?ixlib=rb-1.2.1&q=80&fm=jpg&crop=entropy&cs=tinysrgb&w=200&fit=max"
                     },
                     "links": {
                        "self": "https://api.unsplash.com/photos/PmNjS6b3XP4",
                        "html": "https://unsplash.com/photos/PmNjS6b3XP4",
                        "download": "https://unsplash.com/photos/PmNjS6b3XP4/download",
                        "download_location": "https://api.unsplash.com/photos/PmNjS6b3XP4/download"
                     },
                     "categories": [],
                     "likes": 2135,
                     "liked_by_user": false,
                     "current_user_collections": [],
                     "sponsorship": null,
                     "user": {
                        "id": "7S_pCRiCiQo",
                        "updated_at": "2021-05-17T04:16:39-04:00",
                        "username": "thedakotacorbin",
                        "name": "Dakota Corbin",
                        "first_name": "Dakota",
                        "last_name": "Corbin",
                        "twitter_username": "thedakotacorbin",
                        "portfolio_url": "http://www.dakotacorbin.com",
                        "bio": "Husband | Father | Creator",
                        "location": "Utah, United States",
                        "links": {
                           "self": "https://api.unsplash.com/users/thedakotacorbin",
                           "html": "https://unsplash.com/@thedakotacorbin",
                           "photos": "https://api.unsplash.com/users/thedakotacorbin/photos",
                           "likes": "https://api.unsplash.com/users/thedakotacorbin/likes",
                           "portfolio": "https://api.unsplash.com/users/thedakotacorbin/portfolio",
                           "following": "https://api.unsplash.com/users/thedakotacorbin/following",
                           "followers": "https://api.unsplash.com/users/thedakotacorbin/followers"
                        },
                        "profile_image": {
                           "small": "https://images.unsplash.com/profile-1593623494202-55ffc4dc725cimage?ixlib=rb-1.2.1&q=80&fm=jpg&crop=faces&cs=tinysrgb&fit=crop&h=32&w=32",
                           "medium": "https://images.unsplash.com/profile-1593623494202-55ffc4dc725cimage?ixlib=rb-1.2.1&q=80&fm=jpg&crop=faces&cs=tinysrgb&fit=crop&h=64&w=64",
                           "large": "https://images.unsplash.com/profile-1593623494202-55ffc4dc725cimage?ixlib=rb-1.2.1&q=80&fm=jpg&crop=faces&cs=tinysrgb&fit=crop&h=128&w=128"
                        },
                        "instagram_username": "thedakotacorbin",
                        "total_collections": 0,
                        "total_likes": 1,
                        "total_photos": 44,
                        "accepted_tos": true,
                        "for_hire": false
                     }
                  }
               }
            }
         ]
      },
      {
         "id": "cPYhLpDQu5Y",
         "created_at": "2019-10-27T12:18:52-04:00",
         "updated_at": "2021-05-17T18:10:15-04:00",
         "promoted_at": null,
         "width": 6068,
         "height": 4099,
         "color": "#c0d9f3",
         "blur_hash": "LUIh%1n1E3Si?wDha$t8kst7Ris;",
         "description": null,
         "alt_description": "woman standing near road viewing train and buildings under white and blue sky during daytime",
         "urls": {
            "raw": "https://images.unsplash.com/photo-1572193123914-9677f2162ae5?ixid=MnwxMjA3fDB8MXxzZWFyY2h8MTk3N3x8emVicmF8ZW58MHx8fHwxNjIxMzY4MDcy&ixlib=rb-1.2.1",
            "full": "https://images.unsplash.com/photo-1572193123914-9677f2162ae5?crop=entropy&cs=srgb&fm=jpg&ixid=MnwxMjA3fDB8MXxzZWFyY2h8MTk3N3x8emVicmF8ZW58MHx8fHwxNjIxMzY4MDcy&ixlib=rb-1.2.1&q=85",
            "regular": "https://images.unsplash.com/photo-1572193123914-9677f2162ae5?crop=entropy&cs=tinysrgb&fit=max&fm=jpg&ixid=MnwxMjA3fDB8MXxzZWFyY2h8MTk3N3x8emVicmF8ZW58MHx8fHwxNjIxMzY4MDcy&ixlib=rb-1.2.1&q=80&w=1080",
            "small": "https://images.unsplash.com/photo-1572193123914-9677f2162ae5?crop=entropy&cs=tinysrgb&fit=max&fm=jpg&ixid=MnwxMjA3fDB8MXxzZWFyY2h8MTk3N3x8emVicmF8ZW58MHx8fHwxNjIxMzY4MDcy&ixlib=rb-1.2.1&q=80&w=400",
            "thumb": "https://images.unsplash.com/photo-1572193123914-9677f2162ae5?crop=entropy&cs=tinysrgb&fit=max&fm=jpg&ixid=MnwxMjA3fDB8MXxzZWFyY2h8MTk3N3x8emVicmF8ZW58MHx8fHwxNjIxMzY4MDcy&ixlib=rb-1.2.1&q=80&w=200"
         },
         "links": {
            "self": "https://api.unsplash.com/photos/cPYhLpDQu5Y",
            "html": "https://unsplash.com/photos/cPYhLpDQu5Y",
            "download": "https://unsplash.com/photos/cPYhLpDQu5Y/download",
            "download_location": "https://api.unsplash.com/photos/cPYhLpDQu5Y/download?ixid=MnwxMjA3fDB8MXxzZWFyY2h8MTk3N3x8emVicmF8ZW58MHx8fHwxNjIxMzY4MDcy"
         },
         "categories": [],
         "likes": 40,
         "liked_by_user": false,
         "current_user_collections": [],
         "sponsorship": null,
         "user": {
            "id": "z2MO9smP1ZI",
            "updated_at": "2021-05-18T03:49:51-04:00",
            "username": "imchenyf",
            "name": "YIFEI CHEN",
            "first_name": "YIFEI",
            "last_name": "CHEN",
            "twitter_username": null,
            "portfolio_url": null,
            "bio": "walking&thinking&shooting",
            "location": "CHINA",
            "links": {
               "self": "https://api.unsplash.com/users/imchenyf",
               "html": "https://unsplash.com/@imchenyf",
               "photos": "https://api.unsplash.com/users/imchenyf/photos",
               "likes": "https://api.unsplash.com/users/imchenyf/likes",
               "portfolio": "https://api.unsplash.com/users/imchenyf/portfolio",
               "following": "https://api.unsplash.com/users/imchenyf/following",
               "followers": "https://api.unsplash.com/users/imchenyf/followers"
            },
            "profile_image": {
               "small": "https://images.unsplash.com/profile-1496562934280-5b81c44fec03?ixlib=rb-1.2.1&q=80&fm=jpg&crop=faces&cs=tinysrgb&fit=crop&h=32&w=32",
               "medium": "https://images.unsplash.com/profile-1496562934280-5b81c44fec03?ixlib=rb-1.2.1&q=80&fm=jpg&crop=faces&cs=tinysrgb&fit=crop&h=64&w=64",
               "large": "https://images.unsplash.com/profile-1496562934280-5b81c44fec03?ixlib=rb-1.2.1&q=80&fm=jpg&crop=faces&cs=tinysrgb&fit=crop&h=128&w=128"
            },
            "instagram_username": "imchenyf",
            "total_collections": 2,
            "total_likes": 75,
            "total_photos": 146,
            "accepted_tos": true,
            "for_hire": false
         },
         "tags": [
            {
               "type": "search",
               "title": "asphalt"
            },
            {
               "type": "search",
               "title": "tarmac"
            },
            {
               "type": "search",
               "title": "road"
            }
         ]
      },
      {
         "id": "g4EFm72FpbY",
         "created_at": "2021-04-07T03:53:26-04:00",
         "updated_at": "2021-05-17T09:26:02-04:00",
         "promoted_at": null,
         "width": 4032,
         "height": 2473,
         "color": "#262659",
         "blur_hash": "L74.cMD|WHwdVVabk9jDD~wzkDS%",
         "description": null,
         "alt_description": "traffic light on red light during night time",
         "urls": {
            "raw": "https://images.unsplash.com/photo-1617781921404-75676d04a8db?ixid=MnwxMjA3fDB8MXxzZWFyY2h8MTk3OHx8emVicmF8ZW58MHx8fHwxNjIxMzY4MDcy&ixlib=rb-1.2.1",
            "full": "https://images.unsplash.com/photo-1617781921404-75676d04a8db?crop=entropy&cs=srgb&fm=jpg&ixid=MnwxMjA3fDB8MXxzZWFyY2h8MTk3OHx8emVicmF8ZW58MHx8fHwxNjIxMzY4MDcy&ixlib=rb-1.2.1&q=85",
            "regular": "https://images.unsplash.com/photo-1617781921404-75676d04a8db?crop=entropy&cs=tinysrgb&fit=max&fm=jpg&ixid=MnwxMjA3fDB8MXxzZWFyY2h8MTk3OHx8emVicmF8ZW58MHx8fHwxNjIxMzY4MDcy&ixlib=rb-1.2.1&q=80&w=1080",
            "small": "https://images.unsplash.com/photo-1617781921404-75676d04a8db?crop=entropy&cs=tinysrgb&fit=max&fm=jpg&ixid=MnwxMjA3fDB8MXxzZWFyY2h8MTk3OHx8emVicmF8ZW58MHx8fHwxNjIxMzY4MDcy&ixlib=rb-1.2.1&q=80&w=400",
            "thumb": "https://images.unsplash.com/photo-1617781921404-75676d04a8db?crop=entropy&cs=tinysrgb&fit=max&fm=jpg&ixid=MnwxMjA3fDB8MXxzZWFyY2h8MTk3OHx8emVicmF8ZW58MHx8fHwxNjIxMzY4MDcy&ixlib=rb-1.2.1&q=80&w=200"
         },
         "links": {
            "self": "https://api.unsplash.com/photos/g4EFm72FpbY",
            "html": "https://unsplash.com/photos/g4EFm72FpbY",
            "download": "https://unsplash.com/photos/g4EFm72FpbY/download",
            "download_location": "https://api.unsplash.com/photos/g4EFm72FpbY/download?ixid=MnwxMjA3fDB8MXxzZWFyY2h8MTk3OHx8emVicmF8ZW58MHx8fHwxNjIxMzY4MDcy"
         },
         "categories": [],
         "likes": 0,
         "liked_by_user": false,
         "current_user_collections": [],
         "sponsorship": null,
         "user": {
            "id": "M13oDvcQ-2w",
            "updated_at": "2021-05-18T13:10:10-04:00",
            "username": "jjying",
            "name": "JJ Ying",
            "first_name": "JJ",
            "last_name": "Ying",
            "twitter_username": "JJYing",
            "portfolio_url": "https://instagram.com/jjying/",
            "bio": "UI designer, full-time PSholic, part-time CSSer, blogger @ http://TuYueZhi.com , co-host @ Anyway.FM design podcast",
            "location": "Shanghai, China",
            "links": {
               "self": "https://api.unsplash.com/users/jjying",
               "html": "https://unsplash.com/@jjying",
               "photos": "https://api.unsplash.com/users/jjying/photos",
               "likes": "https://api.unsplash.com/users/jjying/likes",
               "portfolio": "https://api.unsplash.com/users/jjying/portfolio",
               "following": "https://api.unsplash.com/users/jjying/following",
               "followers": "https://api.unsplash.com/users/jjying/followers"
            },
            "profile_image": {
               "small": "https://images.unsplash.com/profile-1486092899496-359010a96a9c?ixlib=rb-1.2.1&q=80&fm=jpg&crop=faces&cs=tinysrgb&fit=crop&h=32&w=32",
               "medium": "https://images.unsplash.com/profile-1486092899496-359010a96a9c?ixlib=rb-1.2.1&q=80&fm=jpg&crop=faces&cs=tinysrgb&fit=crop&h=64&w=64",
               "large": "https://images.unsplash.com/profile-1486092899496-359010a96a9c?ixlib=rb-1.2.1&q=80&fm=jpg&crop=faces&cs=tinysrgb&fit=crop&h=128&w=128"
            },
            "instagram_username": "jjying",
            "total_collections": 10,
            "total_likes": 327,
            "total_photos": 101,
            "accepted_tos": true,
            "for_hire": false
         },
         "tags": [
            {
               "type": "search",
               "title": "asphalt"
            },
            {
               "type": "search",
               "title": "tarmac"
            },
            {
               "type": "search",
               "title": "road"
            }
         ]
      },
      {
         "id": "n0o2X2lWGnI",
         "created_at": "2021-02-27T04:57:28-05:00",
         "updated_at": "2021-05-18T11:37:10-04:00",
         "promoted_at": null,
         "width": 3034,
         "height": 3793,
         "color": "#405959",
         "blur_hash": "LAAdr|9FM|tm%LRjbEtmD%?^IAIA",
         "description": null,
         "alt_description": "people walking on pedestrian lane during daytime",
         "urls": {
            "raw": "https://images.unsplash.com/photo-1614419348516-445835041e02?ixid=MnwxMjA3fDB8MXxzZWFyY2h8MTk3OXx8emVicmF8ZW58MHx8fHwxNjIxMzY4MDcy&ixlib=rb-1.2.1",
            "full": "https://images.unsplash.com/photo-1614419348516-445835041e02?crop=entropy&cs=srgb&fm=jpg&ixid=MnwxMjA3fDB8MXxzZWFyY2h8MTk3OXx8emVicmF8ZW58MHx8fHwxNjIxMzY4MDcy&ixlib=rb-1.2.1&q=85",
            "regular": "https://images.unsplash.com/photo-1614419348516-445835041e02?crop=entropy&cs=tinysrgb&fit=max&fm=jpg&ixid=MnwxMjA3fDB8MXxzZWFyY2h8MTk3OXx8emVicmF8ZW58MHx8fHwxNjIxMzY4MDcy&ixlib=rb-1.2.1&q=80&w=1080",
            "small": "https://images.unsplash.com/photo-1614419348516-445835041e02?crop=entropy&cs=tinysrgb&fit=max&fm=jpg&ixid=MnwxMjA3fDB8MXxzZWFyY2h8MTk3OXx8emVicmF8ZW58MHx8fHwxNjIxMzY4MDcy&ixlib=rb-1.2.1&q=80&w=400",
            "thumb": "https://images.unsplash.com/photo-1614419348516-445835041e02?crop=entropy&cs=tinysrgb&fit=max&fm=jpg&ixid=MnwxMjA3fDB8MXxzZWFyY2h8MTk3OXx8emVicmF8ZW58MHx8fHwxNjIxMzY4MDcy&ixlib=rb-1.2.1&q=80&w=200"
         },
         "links": {
            "self": "https://api.unsplash.com/photos/n0o2X2lWGnI",
            "html": "https://unsplash.com/photos/n0o2X2lWGnI",
            "download": "https://unsplash.com/photos/n0o2X2lWGnI/download",
            "download_location": "https://api.unsplash.com/photos/n0o2X2lWGnI/download?ixid=MnwxMjA3fDB8MXxzZWFyY2h8MTk3OXx8emVicmF8ZW58MHx8fHwxNjIxMzY4MDcy"
         },
         "categories": [],
         "likes": 4,
         "liked_by_user": false,
         "current_user_collections": [],
         "sponsorship": null,
         "user": {
            "id": "aTusdyjq3Wc",
            "updated_at": "2021-05-16T23:42:58-04:00",
            "username": "yeh_che_wei",
            "name": "CHE-WEI YEH",
            "first_name": "CHE-WEI",
            "last_name": "YEH",
            "twitter_username": null,
            "portfolio_url": "https://www.instagram.com/shadowyeh/",
            "bio": "IG\uff1ashadowyeh",
            "location": "Taiwan",
            "links": {
               "self": "https://api.unsplash.com/users/yeh_che_wei",
               "html": "https://unsplash.com/@yeh_che_wei",
               "photos": "https://api.unsplash.com/users/yeh_che_wei/photos",
               "likes": "https://api.unsplash.com/users/yeh_che_wei/likes",
               "portfolio": "https://api.unsplash.com/users/yeh_che_wei/portfolio",
               "following": "https://api.unsplash.com/users/yeh_che_wei/following",
               "followers": "https://api.unsplash.com/users/yeh_che_wei/followers"
            },
            "profile_image": {
               "small": "https://images.unsplash.com/profile-1614168218664-3109a802b91fimage?ixlib=rb-1.2.1&q=80&fm=jpg&crop=faces&cs=tinysrgb&fit=crop&h=32&w=32",
               "medium": "https://images.unsplash.com/profile-1614168218664-3109a802b91fimage?ixlib=rb-1.2.1&q=80&fm=jpg&crop=faces&cs=tinysrgb&fit=crop&h=64&w=64",
               "large": "https://images.unsplash.com/profile-1614168218664-3109a802b91fimage?ixlib=rb-1.2.1&q=80&fm=jpg&crop=faces&cs=tinysrgb&fit=crop&h=128&w=128"
            },
            "instagram_username": "shadowyeh",
            "total_collections": 0,
            "total_likes": 0,
            "total_photos": 119,
            "accepted_tos": true,
            "for_hire": false
         },
         "tags": []
      },
      {
         "id": "J3QZWv6OCBw",
         "created_at": "2017-11-28T00:02:33-05:00",
         "updated_at": "2021-05-18T02:02:38-04:00",
         "promoted_at": "2017-11-28T08:10:10-05:00",
         "width": 5204,
         "height": 7804,
         "color": "#0c2626",
         "blur_hash": "LBA]{N?GD*I?Z$%1t7M{0fWBxZaK",
         "description": null,
         "alt_description": "people walking on road",
         "urls": {
            "raw": "https://images.unsplash.com/photo-1511845241939-402489d3d670?ixid=MnwxMjA3fDB8MXxzZWFyY2h8MTk4MHx8emVicmF8ZW58MHx8fHwxNjIxMzY4MDcy&ixlib=rb-1.2.1",
            "full": "https://images.unsplash.com/photo-1511845241939-402489d3d670?crop=entropy&cs=srgb&fm=jpg&ixid=MnwxMjA3fDB8MXxzZWFyY2h8MTk4MHx8emVicmF8ZW58MHx8fHwxNjIxMzY4MDcy&ixlib=rb-1.2.1&q=85",
            "regular": "https://images.unsplash.com/photo-1511845241939-402489d3d670?crop=entropy&cs=tinysrgb&fit=max&fm=jpg&ixid=MnwxMjA3fDB8MXxzZWFyY2h8MTk4MHx8emVicmF8ZW58MHx8fHwxNjIxMzY4MDcy&ixlib=rb-1.2.1&q=80&w=1080",
            "small": "https://images.unsplash.com/photo-1511845241939-402489d3d670?crop=entropy&cs=tinysrgb&fit=max&fm=jpg&ixid=MnwxMjA3fDB8MXxzZWFyY2h8MTk4MHx8emVicmF8ZW58MHx8fHwxNjIxMzY4MDcy&ixlib=rb-1.2.1&q=80&w=400",
            "thumb": "https://images.unsplash.com/photo-1511845241939-402489d3d670?crop=entropy&cs=tinysrgb&fit=max&fm=jpg&ixid=MnwxMjA3fDB8MXxzZWFyY2h8MTk4MHx8emVicmF8ZW58MHx8fHwxNjIxMzY4MDcy&ixlib=rb-1.2.1&q=80&w=200"
         },
         "links": {
            "self": "https://api.unsplash.com/photos/J3QZWv6OCBw",
            "html": "https://unsplash.com/photos/J3QZWv6OCBw",
            "download": "https://unsplash.com/photos/J3QZWv6OCBw/download",
            "download_location": "https://api.unsplash.com/photos/J3QZWv6OCBw/download?ixid=MnwxMjA3fDB8MXxzZWFyY2h8MTk4MHx8emVicmF8ZW58MHx8fHwxNjIxMzY4MDcy"
         },
         "categories": [],
         "likes": 381,
         "liked_by_user": false,
         "current_user_collections": [],
         "sponsorship": null,
         "user": {
            "id": "rbApLGN_n8M",
            "updated_at": "2021-05-18T14:40:18-04:00",
            "username": "chrisyangchrisfilm",
            "name": "Chris Yang",
            "first_name": "Chris",
            "last_name": "Yang",
            "twitter_username": null,
            "portfolio_url": "http://www.youtube.com/chrisfilmpresents",
            "bio": "Filmmaker, Photographer, Traveler from Taipei Taiwan. \r\nIG: @chris.yang.film\r\nSubscribe Youtube Channel: Chris Film Presents",
            "location": "Taiwan",
            "links": {
               "self": "https://api.unsplash.com/users/chrisyangchrisfilm",
               "html": "https://unsplash.com/@chrisyangchrisfilm",
               "photos": "https://api.unsplash.com/users/chrisyangchrisfilm/photos",
               "likes": "https://api.unsplash.com/users/chrisyangchrisfilm/likes",
               "portfolio": "https://api.unsplash.com/users/chrisyangchrisfilm/portfolio",
               "following": "https://api.unsplash.com/users/chrisyangchrisfilm/following",
               "followers": "https://api.unsplash.com/users/chrisyangchrisfilm/followers"
            },
            "profile_image": {
               "small": "https://images.unsplash.com/profile-1538494708603-f0d01c4cd954?ixlib=rb-1.2.1&q=80&fm=jpg&crop=faces&cs=tinysrgb&fit=crop&h=32&w=32",
               "medium": "https://images.unsplash.com/profile-1538494708603-f0d01c4cd954?ixlib=rb-1.2.1&q=80&fm=jpg&crop=faces&cs=tinysrgb&fit=crop&h=64&w=64",
               "large": "https://images.unsplash.com/profile-1538494708603-f0d01c4cd954?ixlib=rb-1.2.1&q=80&fm=jpg&crop=faces&cs=tinysrgb&fit=crop&h=128&w=128"
            },
            "instagram_username": "chris.yang.film",
            "total_collections": 0,
            "total_likes": 239,
            "total_photos": 283,
            "accepted_tos": true,
            "for_hire": false
         },
         "tags": [
            {
               "type": "search",
               "title": "road"
            },
            {
               "type": "search",
               "title": "japan"
            },
            {
               "type": "landing_page",
               "title": "city",
               "source": {
                  "ancestry": {
                     "type": {
                        "slug": "wallpapers",
                        "pretty_slug": "HD Wallpapers"
                     },
                     "category": {
                        "slug": "travel",
                        "pretty_slug": "Travel"
                     },
                     "subcategory": {
                        "slug": "city",
                        "pretty_slug": "City"
                     }
                  },
                  "title": "HD City Wallpapers",
                  "subtitle": "Download Free City Wallpapers",
                  "description": "Choose from a curated selection of city wallpapers for your mobile and desktop screens. Always free on Unsplash.",
                  "meta_title": "City Wallpapers: Free HD Download [500+ HQ] | Unsplash",
                  "meta_description": "Choose from hundreds of free city wallpapers. Download HD wallpapers for free on Unsplash.",
                  "cover_photo": {
                     "id": "Nyvq2juw4_o",
                     "created_at": "2016-10-31T20:26:28-04:00",
                     "updated_at": "2021-05-16T11:01:14-04:00",
                     "promoted_at": "2016-10-31T20:26:28-04:00",
                     "width": 3465,
                     "height": 2131,
                     "color": "#0c2640",
                     "blur_hash": "LhEMa,W=WVWW_4kBjtW=?bkBaefR",
                     "description": "City architecture and skyscrapers near waterfront",
                     "alt_description": "white and brown city buildings during daytime",
                     "urls": {
                        "raw": "https://images.unsplash.com/photo-1477959858617-67f85cf4f1df?ixlib=rb-1.2.1",
                        "full": "https://images.unsplash.com/photo-1477959858617-67f85cf4f1df?ixlib=rb-1.2.1&q=85&fm=jpg&crop=entropy&cs=srgb",
                        "regular": "https://images.unsplash.com/photo-1477959858617-67f85cf4f1df?ixlib=rb-1.2.1&q=80&fm=jpg&crop=entropy&cs=tinysrgb&w=1080&fit=max",
                        "small": "https://images.unsplash.com/photo-1477959858617-67f85cf4f1df?ixlib=rb-1.2.1&q=80&fm=jpg&crop=entropy&cs=tinysrgb&w=400&fit=max",
                        "thumb": "https://images.unsplash.com/photo-1477959858617-67f85cf4f1df?ixlib=rb-1.2.1&q=80&fm=jpg&crop=entropy&cs=tinysrgb&w=200&fit=max"
                     },
                     "links": {
                        "self": "https://api.unsplash.com/photos/Nyvq2juw4_o",
                        "html": "https://unsplash.com/photos/Nyvq2juw4_o",
                        "download": "https://unsplash.com/photos/Nyvq2juw4_o/download",
                        "download_location": "https://api.unsplash.com/photos/Nyvq2juw4_o/download"
                     },
                     "categories": [],
                     "likes": 2301,
                     "liked_by_user": false,
                     "current_user_collections": [],
                     "sponsorship": null,
                     "user": {
                        "id": "1--L3vNK0TA",
                        "updated_at": "2021-05-16T20:22:43-04:00",
                        "username": "peterlaster",
                        "name": "Pedro Lastra",
                        "first_name": "Pedro",
                        "last_name": "Lastra",
                        "twitter_username": null,
                        "portfolio_url": "https://www.flickr.com/photos/lastingimages/",
                        "bio": null,
                        "location": null,
                        "links": {
                           "self": "https://api.unsplash.com/users/peterlaster",
                           "html": "https://unsplash.com/@peterlaster",
                           "photos": "https://api.unsplash.com/users/peterlaster/photos",
                           "likes": "https://api.unsplash.com/users/peterlaster/likes",
                           "portfolio": "https://api.unsplash.com/users/peterlaster/portfolio",
                           "following": "https://api.unsplash.com/users/peterlaster/following",
                           "followers": "https://api.unsplash.com/users/peterlaster/followers"
                        },
                        "profile_image": {
                           "small": "https://images.unsplash.com/placeholder-avatars/extra-large.jpg?ixlib=rb-1.2.1&q=80&fm=jpg&crop=faces&cs=tinysrgb&fit=crop&h=32&w=32",
                           "medium": "https://images.unsplash.com/placeholder-avatars/extra-large.jpg?ixlib=rb-1.2.1&q=80&fm=jpg&crop=faces&cs=tinysrgb&fit=crop&h=64&w=64",
                           "large": "https://images.unsplash.com/placeholder-avatars/extra-large.jpg?ixlib=rb-1.2.1&q=80&fm=jpg&crop=faces&cs=tinysrgb&fit=crop&h=128&w=128"
                        },
                        "instagram_username": null,
                        "total_collections": 10,
                        "total_likes": 47,
                        "total_photos": 86,
                        "accepted_tos": false,
                        "for_hire": false
                     }
                  }
               }
            }
         ]
      }
   ]
}